Workbook
Name Referred: LOOKUPS!$C$2:$C$9
Name Report_Requested: LOOKUPS!$D$2:$D$8
Name Wtg_Att_Mgr_Dec: LOOKUPS!$E$2:$E$12
Name Wtg_Referral_Dec: LOOKUPS!$F$2:$F$13

Sheet MASTER
A1: Row Status | B1: Period | C1: Incident Number | D1: Incident Date | E1: Headcode | F1: Train | G1: Incident Location | H1: TARA Primary Delay Minutes | I1: TARA Canx | J1: Primary Mins Sum | K1: Total Mins | L1: Sum Canx | M1: Equipment Bugle | N1: Vehicle No. | O1: Unit No. | P1: Coupled Unit No. | Q1: 5-9 Car | R1: Train Type | S1: Train Accepted | T1: LNER Investigation Notes | U1: Hitachi Investigation Notes / SAP info / Root Cause | V1: LNER Status Notes | W1: Bugle Mgr | X1: Trust Mgr | Y1: Inc Cause | Z1: Root Cause | AA1: Bugle Dispute Status | AB1: Bugle Status | AC1: LNER Fleet Status | AD1: Report Requested From/Delay Attributed To: | AE1: Master Incident Number | AF1: Date Report Requested/Referred or Delay Closed Out | AG1: Hitachi Status | AH1: Tech | AI1: TIN | AJ1: KPI Code | AK1: Cause Code | AL1: System | AM1: Subsystem | AN1: Failure | AO1: Engineering Comments | AP1: EFC (if Required) In Progress? | AQ1: PHRD? | AR1: PHRD Number | AS1: PIP/MOD Recommended?
A2: New | B2: 2612 | C2: 192749 | D2: 46065 | E2: 1E15 | F2: 09:52 ABERDEEN to KINGS X | G2: EDB MNK | H2: 17 | I2: 0 | J2: 17 | K2: 83 | L2: 0 | M2: 800106 | N2: 811106 | O2: 800106 | Q2: 9 | R2: 80x | S2: 43550 | T2: 1E15 POWER FAULT EDB MNK LVL2 Driver NED 52 contacted LNER STSM to advise that they had come to a stand between Portobello Jn and Musselburgh with a check pan alarm. They advised that they came to a stand and lowered their pantograph in order to complete their checks. They advised that all is okay and have spoken to Hitachi and confirmed that they are ok to continue forward at linespeed using their pantograph. TMS 6602 No Current Draw from OHL LOG 260212-79 refers. SAP 8347717 refers. | U2: Under investigation. | V2: 161321 is the exact same. Both to be disputed with HRL until suitable explanation can be obtained. Disputed with HRL. JC 13/02 | W2: MHB1 | X2: MHB1 | Y2: M1 | AA2: D | AB2: New | AC2: Refer to Level 2 | AE2: 260212-192749 | AG2: Investigation | AI2: =IF(AD2="Availability", 0, IF(AND(AE2="Y", OR(J2>2, L2>0)), 1, 0)) -> 0 | AJ2: 701D | AL2: =IFERROR(IF(AK2="", "", _xlfn.XLOOKUP(AK2, CODES!A:A,CODES!E:E)), "") | AM2: =IFERROR(IF(AK2="", "", _xlfn.XLOOKUP(AK2, CODES!A:A,CODES!G:G)), "") | AN2: =IFERROR(IF(AK2="", "", _xlfn.XLOOKUP(AK2, CODES!A:A,CODES!I:I)), "")
A3: New | B3: 2612 | C3: 192000 | D3: 46065 | E3: 5S08 | F3: 06:34 FERMEPARK to KINGS X | G3: FRMPKRS | H3: 5 | I3: 0 | J3: 5 | K3: 5 | L3: 0 | M3: Undefined | O3: 801208 | Q3: 9 | R3: 80x | T3: 5S08 DEPOT OPS FRMPKRS THE DEPOT REPORT THAT 5S08 WAS HELD AT K451 WAITING FOR THE SIGNAL TO DEPART. | U3: HRE Reject, MTIN – No. Depot report Unit held at K451 waiting for the signal to depart. Class 5 only delay. | V3: TMV/dispute raised. JC 13/02 | W3: MHBJ | X3: MHBJ | Y3: MU | AA3: A | AB3: New | AC3: Investigation | AE3: 260212-192000 | AG3: Rejected - Class 3/5 | AH3: N | AI3: =IF(AD3="Availability", 0, IF(AND(AE3="Y", OR(J3>2, L3>0)), 1, 0)) -> 0 | AJ3: 701A | AK3: 1DB | AL3: =IFERROR(IF(AK3="", "", _xlfn.XLOOKUP(AK3, CODES!A:A,CODES!E:E)), "") -> Operational | AM3: =IFERROR(IF(AK3="", "", _xlfn.XLOOKUP(AK3, CODES!A:A,CODES!G:G)), "") -> NR | AN3: =IFERROR(IF(AK3="", "", _xlfn.XLOOKUP(AK3, CODES!A:A,CODES!I:I)), "") -> Regulation | AO3: Unit late off depot.
A4: New | B4: 2612 | C4: 191778 | D4: 46065 | E4: 5A02 | G4: XNL | J4: 59 | K4: 143 | L4: 0 | M4: NL12 | N4: 82212 | O4: NL12 | Q4: 11 | R4: 225 | T4: 5A02 ABOVE SBAR XNL…..No bogie brake readings | U4: Quirk of the DVT brake system…..Spare set launched | W4: MHBC | X4: MHBC | Y4: MN | AA4: D | AB4: New | AC4: Investigation | AE4: 260212-191778 | AI4: =IF(AD4="Availability", 0, IF(AND(AE4="Y", OR(J4>2, L4>0)), 1, 0)) -> 0 | AJ4: 701D | AL4: =IFERROR(IF(AK4="", "", _xlfn.XLOOKUP(AK4, CODES!A:A,CODES!E:E)), "") | AM4: =IFERROR(IF(AK4="", "", _xlfn.XLOOKUP(AK4, CODES!A:A,CODES!G:G)), "") | AN4: =IFERROR(IF(AK4="", "", _xlfn.XLOOKUP(AK4, CODES!A:A,CODES!I:I)), "")
A5: New | B5: 2612 | C5: 191716 | D5: 46065 | E5: 3Y03 | F5: 04:35 DONCARIEP to YORK Running as 04:57 DONCASTER to YORK | G5: DON | H5: 10 | I5: 0 | J5: 10 | K5: 21 | L5: 0 | M5: 800202 | O5: 800202 | Q5: 5 | R5: 80x | S5: 43819 | T5: 3Y03 UNIT FLT DON ADVISED BY NETWORK RAIL THAT 3Y03 $04:57 DONCASTER - YORK| IS CURRENTLY BEING DELAYED AT DONCASTER DU ETO REPORTS OF HAVING TROUBLE BUILDING AIR. 1Y01 CURRENTLY BEING HELD OUTSIDE OF THE STATION WAITING FOR A PLATFORM. | U5: HRE Reject, MTIN – No, Unit outstabled at Doncaster due to mainline disruption 11/02. Low main res air pressure and associated issues, cleared with an aux off/on of the Unit after air pressure had built up on the Unit. Class 3 only delay. | V5: Drvier report requested - JM. JC 13/02 | W5: MHB1 | X5: MHB1 | Y5: M8 | AA5: A | AB5: New | AC5: Investigation | AE5: 260212-191716 | AG5: Rejected | AH5: N | AI5: =IF(AD5="Availability", 0, IF(AND(AE5="Y", OR(J5>2, L5>0)), 1, 0)) -> 0 | AJ5: 701D | AL5: =IFERROR(IF(AK5="", "", _xlfn.XLOOKUP(AK5, CODES!A:A,CODES!E:E)), "") | AM5: =IFERROR(IF(AK5="", "", _xlfn.XLOOKUP(AK5, CODES!A:A,CODES!G:G)), "") | AN5: =IFERROR(IF(AK5="", "", _xlfn.XLOOKUP(AK5, CODES!A:A,CODES!I:I)), "")
A6: Root Cause, Bugle Dispute Status | B6: 2612 | C6: 190994 | D6: 46064 | E6: 1D26 | F6: 18:03 KINGS X to SKIPTON | G6: DON | H6: 11 | I6: 0 | J6: 11 | K6: 34 | L6: 0 | M6: 800/801 | O6: 800203 | P6: 801106 | Q6: 5 | R6: 80x | S6: 43728 | T6: 1D26 11 OVERTIME DON 19:55 driver reports dispatch staff report smoke from the underframe at Doncaster Station. MC asked if the GU's are pre heating. Driver reports they were. Advised that a relief driver is going to inspect the area reported. Informed driver that smoke is likely due to GU preheating. Relief driver confirmed no evidence of smoke or fire present. Happy for the unit to proceed forward, driver is going to have a check again at LDS and report back. LOG 260211-68 refers. *Safety of the line* | U6: Under investigation. | W6: MHB2 | X6: MHB2 | Y6: M9 | Z6: M9 | AA6: A | AB6: Accepted | AC6: Investigation | AE6: 260211-190994 | AG6: Investigation | AI6: =IF(AD6="Availability", 0, IF(AND(AE6="Y", OR(J6>2, L6>0)), 1, 0)) -> 0 | AJ6: 701D | AL6: =IFERROR(IF(AK6="", "", _xlfn.XLOOKUP(AK6, CODES!A:A,CODES!E:E)), "") | AM6: =IFERROR(IF(AK6="", "", _xlfn.XLOOKUP(AK6, CODES!A:A,CODES!G:G)), "") | AN6: =IFERROR(IF(AK6="", "", _xlfn.XLOOKUP(AK6, CODES!A:A,CODES!I:I)), "")
A7: Root Cause | B7: 2612 | C7: 189004 | D7: 46064 | E7: 5Y26 | F7: 22:26 KINGS X to BOUNDGNCS | G7: BNDSGRN | H7: 33 | I7: 0 | J7: 33 | K7: 33 | L7: 0 | M7: 801225 | O7: 801225 | Q7: 9 | R7: 80x | S7: 43868 | T7: 5Y26 WTG ACCEP BNDSGRN 5Y26 SHOULD BEPART FMP AT 22:40 TMV REPLY SHOWS DEPARTING 22:55 NO INFOAMTION IN TAS. MORE INFOMATION REQUIED FROM BN/FMP DEPOT. | U7: HRE Reject, MTIN – No. Depot report congestion. Class 5 only delay. | W7: MHBJ | X7: MHBJ | Y7: MU | Z7: MU | AA7: A | AB7: Accepted | AC7: Accepted | AE7: 260211-189004 | AG7: Rejected - Class 3/5 | AH7: N | AI7: =IF(AD7="Availability", 0, IF(AND(AE7="Y", OR(J7>2, L7>0)), 1, 0)) -> 0 | AJ7: 701A | AK7: 1BD | AL7: =IFERROR(IF(AK7="", "", _xlfn.XLOOKUP(AK7, CODES!A:A,CODES!E:E)), "") -> Operational | AM7: =IFERROR(IF(AK7="", "", _xlfn.XLOOKUP(AK7, CODES!A:A,CODES!G:G)), "") -> Depot | AN7: =IFERROR(IF(AK7="", "", _xlfn.XLOOKUP(AK7, CODES!A:A,CODES!I:I)), "") -> Process | AO7: Awaiting acceptance onto depot.
A8: Root Cause, Bugle Dispute Status | B8: 2612 | C8: 188162 | D8: 46063 | E8: 1S19 | F8: 14:03 KINGS X to ABERDEEN | G8: DAR | H8: 7 | I8: 0 | J8: 7 | K8: 7 | L8: 0 | M8: 800110 | N8: 816110 | O8: 800110 | Q8: 9 | R8: 80x | S8: 43584 | T8: 1S19 7 OVERTIME DAR Train at a stand at Darlington due to TM unaware that the AIVR was attached underneath 800110. Brief's have gone out and on the update today. LOG 260210-68 refers. | U8: HRE Reject, MTIN – No. Station overtime at Darlington after the Signaller reported to the Driver that there was a strange light underneath the train having been reported by a TPE service. On inspection is was confirmed to be NR AIVR monitoring equipment fitted to the train. | V8: Dispute raised. JC 11/02 Able to dispute. JC 11/02 | W8: MHB1 | X8: MHB1 | Y8: M9 | AA8: D | AB8: New | AC8: Wtg_Att_Mgr_Dec | AE8: 260210-188162 | AG8: Rejected | AH8: N | AI8: =IF(AD8="Availability", 0, IF(AND(AE8="Y", OR(J8>2, L8>0)), 1, 0)) -> 0 | AJ8: 701D | AK8: 1DE | AL8: =IFERROR(IF(AK8="", "", _xlfn.XLOOKUP(AK8, CODES!A:A,CODES!E:E)), "") -> Operational | AM8: =IFERROR(IF(AK8="", "", _xlfn.XLOOKUP(AK8, CODES!A:A,CODES!G:G)), "") -> NR | AN8: =IFERROR(IF(AK8="", "", _xlfn.XLOOKUP(AK8, CODES!A:A,CODES!I:I)), "") -> Other | AO8: TM unaware of AIVR equipment being installed on the train.
A9: Root Cause | B9: 2612 | C9: 187971 | D9: 46063 | E9: 1D20 | F9: 15:10 London Kings Cross - Leeds | G9: PBO | J9: 3 | K9: 11 | L9: 0 | M9: NL12 | N9: 12404 | O9: NL12 | Q9: 11 | R9: 225 | T9: 1D20 3 OVERTIME PBO | U9: Rough riding and knocking noise from underframe | V9: WO 5089017 Centre casting shim disintegrated, same renewed & No's 2 & 3 yaw dampers renewed | W9: MHBB | X9: MHBB | Y9: M9 | AA9: A | AB9: New | AC9: Accepted | AE9: 260210-187971 | AH9: Y | AI9: =IF(AD9="Availability", 0, IF(AND(AE9="Y", OR(J9>2, L9>0)), 1, 0)) -> 0 | AJ9: 701D | AL9: =IFERROR(IF(AK9="", "", _xlfn.XLOOKUP(AK9, CODES!A:A,CODES!E:E)), "") | AM9: =IFERROR(IF(AK9="", "", _xlfn.XLOOKUP(AK9, CODES!A:A,CODES!G:G)), "") | AN9: =IFERROR(IF(AK9="", "", _xlfn.XLOOKUP(AK9, CODES!A:A,CODES!I:I)), "")
A10: Reassigned to Fleet, Bugle Mgr, Trust Mgr, Inc Cause, Root Cause, Bugle Dispute Status | B10: 2612 | C10: 187126 | D10: 46063 | E10: 3A12 | F10: 07:15 DONCARIEP to LEEDS | G10: LDS | H10: 0 | I10: 1 | J10: 0 | K10: 2 | L10: 1 | M10: 800111 | O10: 801201 | Q10: 9 | R10: 80x | S10: 44077 | T10: 3A12 CANCELLED DONCIEP 3A12 EXISTS BUT STARTED AT NEVILLE HILL VICE DON IEP. | U10: HRE Reject, MTIN – No. 3A12 formed from Unit 801021 departing from Neville Hill vice DON IEP due to the ongoing investigation into a TMS Brake discrepancy fault on Unit 800111 reported 09/02. 3A12 canx DON IEP - LDS. Class 3 only delay. | W10: MHB1 | X10: MHB1 | Y10: MS | Z10: MS | AA10: A | AB10: Accepted | AC10: Accepted | AE10: 260210-187126 | AG10: Rejected - Class 3/5 | AH10: N | AI10: =IF(AD10="Availability", 0, IF(AND(AE10="Y", OR(J10>2, L10>0)), 1, 0)) -> 0 | AJ10: 701A | AK10: 1CC | AL10: =IFERROR(IF(AK10="", "", _xlfn.XLOOKUP(AK10, CODES!A:A,CODES!E:E)), "") -> Operational | AM10: =IFERROR(IF(AK10="", "", _xlfn.XLOOKUP(AK10, CODES!A:A,CODES!G:G)), "") -> Control | AN10: =IFERROR(IF(AK10="", "", _xlfn.XLOOKUP(AK10, CODES!A:A,CODES!I:I)), "") -> HRL CPC | AO10: Unit started XNL vice Doncaster IEP.
A11: Root Cause | B11: 2612 | C11: 186855 | D11: 46063 | E11: 1A05 | F11: 06:05 Leeds - London Kings Cross | G11: NNG | J11: 4 | K11: 32 | L11: 0 | M11: NL16 | N11: 91111 | O11: NL16 | Q11: 11 | R11: 225 | T11: 1A05 4 OVERTIME NNG | U11: Set will not go above 110mph | V11: WO 5089002 E70 microswitch corrected | W11: MHBA | X11: MHBA | Y11: MB | AA11: A | AB11: New | AC11: Accepted | AE11: 260210-186855 | AH11: N | AI11: =IF(AD11="Availability", 0, IF(AND(AE11="Y", OR(J11>2, L11>0)), 1, 0)) -> 0 | AJ11: 701D | AL11: =IFERROR(IF(AK11="", "", _xlfn.XLOOKUP(AK11, CODES!A:A,CODES!E:E)), "") | AM11: =IFERROR(IF(AK11="", "", _xlfn.XLOOKUP(AK11, CODES!A:A,CODES!G:G)), "") | AN11: =IFERROR(IF(AK11="", "", _xlfn.XLOOKUP(AK11, CODES!A:A,CODES!I:I)), "")
A12: Root Cause | B12: 2612 | C12: 185801 | D12: 46062 | E12: 1E17 | F12: 13:30 EDINBURGH to KINGS X | G12: DON DONCLCJ | H12: 2 | I12: 0 | J12: 2 | K12: 8 | L12: 0 | M12: 801229 | N12: 825229 | O12: 801229 | Q12: 9 | R12: 80x | S12: 43972 | T12: 1E17 2 LOST DON DONCLCJ TRACTION CONVERTOR ISOLATED IN 825229 / SET 801229 COACH H. SAP 8326757 refers. RES 92764 refers - open for 13 days. | U12: MTIN NO, HRE REJECT - Sub threshold delay. | W12: MHB2 | X12: MHB2 | Y12: MD | AA12: D | AB12: New | AC12: Accepted | AE12: 260209-185801 | AG12: Rejected - Sub Threshold | AH12: N | AI12: =IF(AD12="Availability", 0, IF(AND(AE12="Y", OR(J12>2, L12>0)), 1, 0)) -> 0 | AJ12: 701D | AK12: PH6 | AL12: =IFERROR(IF(AK12="", "", _xlfn.XLOOKUP(AK12, CODES!A:A,CODES!E:E)), "") -> Traction and Power Equipment | AM12: =IFERROR(IF(AK12="", "", _xlfn.XLOOKUP(AK12, CODES!A:A,CODES!G:G)), "") -> Traction Converter | AN12: =IFERROR(IF(AK12="", "", _xlfn.XLOOKUP(AK12, CODES!A:A,CODES!I:I)), "") -> Fault not Investigated | AO12: Sub-threshold delay, Traction Converter isolated.
A13: Root Cause | B13: 2612 | C13: 185246 | D13: 46062 | E13: 1E16 | F13: 13:00 EDINBURGH to KINGS X | G13: NCL | H13: 14 | I13: 0 | J13: 14 | K13: 21 | L13: 0 | M13: 801202 | N13: 826202 | O13: 801202 | Q13: 9 | R13: 80x | S13: 43988 | T13: 1E16 14 OVERTIME NCL Smoke detection activation. CCTV suggests person in toilet was possibly vaping. LOG 260209-45 refers. SAP 8342594 refers. | U13: MTIN NO, HRE REJECT - CCTV review confirms a passenger entering the toilet at the time of the alert and thought to have been smoking/vaping in the toilet. HFMT historical events have been monitored since and no further TMS0305 events have occurred. | V13: request to be referred to passenger vandalism code. JC 10/02 Crew reports requested due to time taken to reset. JC 11/02 Reports received, details requested from HRL. JC 11/02 14:20 - 14:38 Details passed onto JP. JC 13/02 | W13: MHB2 | X13: MHB2 | Y13: MT | AA13: D | AB13: New | AC13: Wtg_Att_Mgr_Dec | AE13: 260209-185246 | AG13: Rejected | AH13: N | AI13: =IF(AD13="Availability", 0, IF(AND(AE13="Y", OR(J13>2, L13>0)), 1, 0)) -> 0 | AJ13: 701D | AK13: 2BN | AL13: =IFERROR(IF(AK13="", "", _xlfn.XLOOKUP(AK13, CODES!A:A,CODES!E:E)), "") -> LNER | AM13: =IFERROR(IF(AK13="", "", _xlfn.XLOOKUP(AK13, CODES!A:A,CODES!G:G)), "") -> Other | AN13: =IFERROR(IF(AK13="", "", _xlfn.XLOOKUP(AK13, CODES!A:A,CODES!I:I)), "") -> Passenger Vandalism | AO13: Passenger thought to have been vaping in toilet at time of smoke alarm.
A14: Root Cause | B14: 2612 | C14: 185048 | D14: 46062 | E14: 1B86 | F14: 12:47 KINGS X to LINCLNCEN | G14: KGX | H14: 15 | I14: 0 | J14: 15 | K14: 31 | L14: 0 | M14: 800206 | O14: 800206 | Q14: 5 | R14: 80x | S14: 43721 | T14: 1B86 15 LATE START KGX Low Air at departure, possible set up issue when swapping pans around. LOG 260209-43 refers. SAP 8342602 refers. | U14: MTIN NO, HRE REJECT - Driver error. | V14: referral request sent to HM. JC 10/02 | W14: MHB1 | X14: MHB1 | Y14: MD | AA14: D | AB14: New | AC14: Wtg_Att_Mgr_Dec | AE14: 260209-185048 | AG14: Rejected | AH14: N | AI14: =IF(AD14="Availability", 0, IF(AND(AE14="Y", OR(J14>2, L14>0)), 1, 0)) -> 0 | AJ14: 701D | AK14: 1AA | AL14: =IFERROR(IF(AK14="", "", _xlfn.XLOOKUP(AK14, CODES!A:A,CODES!E:E)), "") -> Operational | AM14: =IFERROR(IF(AK14="", "", _xlfn.XLOOKUP(AK14, CODES!A:A,CODES!G:G)), "") -> Staff | AN14: =IFERROR(IF(AK14="", "", _xlfn.XLOOKUP(AK14, CODES!A:A,CODES!I:I)), "") -> Driver | AO14: Driver did not carry out power configuration correctly.
A15: Root Cause | B15: 2612 | C15: 184308 | D15: 46062 | E15: 1A07 | F15: 06:30 BRADFORSQ to KINGS X | G15: LDS | H15: 4 | I15: 0 | J15: 4 | K15: 4 | L15: 0 | M15: 801204 | N15: 821204 | O15: 801204 | Q15: 9 | R15: 80x | S15: 44005 | T15: 1A07 4 OVERTIME LDS Driver working 1A07 reports that a TRI has advised that the 821 pan has a very thin carbon and locked it out, driver has been advised to use the alternative pan. LOG 260209-35 refers. SAP 8327670 refers. | U15: Under Investigation. | W15: MHB2 | X15: MHB2 | Y15: M1 | AA15: A | AB15: New | AC15: Investigation | AE15: 260209-184308 | AG15: Investigation | AI15: =IF(AD15="Availability", 0, IF(AND(AE15="Y", OR(J15>2, L15>0)), 1, 0)) -> 0 | AJ15: 701D | AL15: =IFERROR(IF(AK15="", "", _xlfn.XLOOKUP(AK15, CODES!A:A,CODES!E:E)), "") | AM15: =IFERROR(IF(AK15="", "", _xlfn.XLOOKUP(AK15, CODES!A:A,CODES!G:G)), "") | AN15: =IFERROR(IF(AK15="", "", _xlfn.XLOOKUP(AK15, CODES!A:A,CODES!I:I)), "")
A16: Root Cause | B16: 2612 | C16: 184293 | D16: 46062 | E16: 3A11 | F16: 06:40 NEVHILL D to BRADFORSQ | G16: XNL | H16: 7 | I16: 0 | J16: 7 | K16: 7 | L16: 0 | M16: 801101/03 | O16: 801101 | P16: 801103 | Q16: 5 | R16: 80x | S16: 43700 | T16: 3A11 7 LATE START XNL Awaiting depot report. | U16: HRE Reject, MTIN – No. Depot report Unit held waiting for the signal to depart. Class 3 only delay. | V16: TMV check required. | W16: MHBM | X16: MHBM | Y16: MU | AA16: A | AB16: New | AC16: Wtg_Att_Mgr_Dec | AE16: 260209-184293 | AG16: Rejected - Class 3/5 | AH16: N | AI16: =IF(AD16="Availability", 0, IF(AND(AE16="Y", OR(J16>2, L16>0)), 1, 0)) -> 0 | AJ16: 701A | AK16: 1BD | AL16: =IFERROR(IF(AK16="", "", _xlfn.XLOOKUP(AK16, CODES!A:A,CODES!E:E)), "") -> Operational | AM16: =IFERROR(IF(AK16="", "", _xlfn.XLOOKUP(AK16, CODES!A:A,CODES!G:G)), "") -> Depot | AN16: =IFERROR(IF(AK16="", "", _xlfn.XLOOKUP(AK16, CODES!A:A,CODES!I:I)), "") -> Process
A17: Root Cause | B17: 2612 | C17: 184268 | D17: 46062 | E17: 1Y04 | F17: 05:27 NCASTLCEN to KINGS X | G17: SHFTHLJ TEMPLHJ | H17: 11 | I17: 0 | J17: 11 | K17: 11 | L17: 0 | M17: 801201 | O17: 801201 | Q17: 9 | R17: 80x | S17: 44077 | T17: 1Y04 11 LOST SHFTHLJ TEMPLH CCIL reports that the driver of 1Y04 reported a loud bang underneath the train on the approach to Heck Ground Frame. *Safety of the line, FFCCTV requested for review* LOG 260209-34 refers. | U17: HRE Reject, MTIN – No. DVR of 1Y04 reports a loud bang underneath the train on the approach to Heck Ground Frame. Delays incurred by 1S02 & 1A90 examining the UM & DM lines with nothing found. | W17: MHB2 | X17: MHB2 | Y17: M9 | AA17: D | AB17: New | AC17: Wtg_Att_Mgr_Dec | AE17: 260209-184268 | AG17: Rejected | AH17: N | AI17: =IF(AD17="Availability", 0, IF(AND(AE17="Y", OR(J17>2, L17>0)), 1, 0)) -> 0 | AJ17: 701D | AK17: CFA | AL17: =IFERROR(IF(AK17="", "", _xlfn.XLOOKUP(AK17, CODES!A:A,CODES!E:E)), "") -> Bodyshell and Exterior | AM17: =IFERROR(IF(AK17="", "", _xlfn.XLOOKUP(AK17, CODES!A:A,CODES!G:G)), "") -> Structure | AN17: =IFERROR(IF(AK17="", "", _xlfn.XLOOKUP(AK17, CODES!A:A,CODES!I:I)), "") -> Underframe | AO17: Safety of the line report.
A18: Root Cause | B18: 2612 | C18: 184254 | D18: 46062 | E18: 1N01 | F18: 06:33 KINGS X to NCASTLCEN | G18: KGX | H18: 11 | I18: 0 | J18: 11 | K18: 11 | L18: 0 | M18: 801214 | N18: 821214 | O18: 801214 | Q18: 9 | R18: 80x | S18: 43943 | T18: 1N01 11 LATE START KGX DSD Pedal unable to cancel LOG 260209-32 refers. SAP 8342124 refers. | U18: MTIN YES, HRE ACCEPT - Budget Lock lid left open in error after planned maintenance, M/H error. | W18: MHB2 | X18: MHB2 | Y18: M8 | AA18: A | AB18: New | AC18: Accepted | AE18: 260209-184254 | AG18: Accepted | AH18: Y | AI18: =IF(AD18="Availability", 0, IF(AND(AE18="Y", OR(J18>2, L18>0)), 1, 0)) -> 0 | AJ18: 701D | AK18: SD7 | AL18: =IFERROR(IF(AK18="", "", _xlfn.XLOOKUP(AK18, CODES!A:A,CODES!E:E)), "") -> Safety System | AM18: =IFERROR(IF(AK18="", "", _xlfn.XLOOKUP(AK18, CODES!A:A,CODES!G:G)), "") -> DSD | AN18: =IFERROR(IF(AK18="", "", _xlfn.XLOOKUP(AK18, CODES!A:A,CODES!I:I)), "") -> Non Technical | AO18: Budget Lock lid on DSD pedal left open in error after planned maintenance, M/H error.
A19: Root Cause | B19: 2612 | C19: 184173 | D19: 46062 | E19: 1A02 | F19: 05:00 Leeds - London Kings Cross | G19: LDS | J19: 0 | K19: 16 | L19: 2 | M19: NL12 | N19: 82212 | O19: NL12 | Q19: 11 | R19: 225 | T19: 1A02 CANCELLED LDS…..No bogie brake readings | U19: Quirk of the DVT brake system | V19: WO 5088976 | W19: MHBC | X19: MHBC | Y19: MN | AA19: A | AB19: New | AC19: Wtg_Att_Mgr_Dec | AE19: 260209-184173 | AI19: =IF(AD19="Availability", 0, IF(AND(AE19="Y", OR(J19>2, L19>0)), 1, 0)) -> 0 | AJ19: 701D | AL19: =IFERROR(IF(AK19="", "", _xlfn.XLOOKUP(AK19, CODES!A:A,CODES!E:E)), "") | AM19: =IFERROR(IF(AK19="", "", _xlfn.XLOOKUP(AK19, CODES!A:A,CODES!G:G)), "") | AN19: =IFERROR(IF(AK19="", "", _xlfn.XLOOKUP(AK19, CODES!A:A,CODES!I:I)), "")
A20: Root Cause | B20: 2612 | C20: 183386 | D20: 46061 | E20: 1A27 | F20: 15:34 Bradford Foster Square - London Kings Cross | G20: WKF | J20: 2 | K20: 3 | L20: 0 | M20: NL08 | N20: 91109 | O20: NL08 | Q20: 11 | R20: 225 | T20: 1A27 2 LOST WHITEHLJN WKF…..Adhesion | U20: Adhesion | V20: Adhesion | W20: MHBA | X20: MHBA | Y20: MP | AA20: A | AB20: New | AC20: Accepted | AE20: 260208-183386 | AH20: N | AI20: =IF(AD20="Availability", 0, IF(AND(AE20="Y", OR(J20>2, L20>0)), 1, 0)) -> 0 | AJ20: 750 | AL20: =IFERROR(IF(AK20="", "", _xlfn.XLOOKUP(AK20, CODES!A:A,CODES!E:E)), "") | AM20: =IFERROR(IF(AK20="", "", _xlfn.XLOOKUP(AK20, CODES!A:A,CODES!G:G)), "") | AN20: =IFERROR(IF(AK20="", "", _xlfn.XLOOKUP(AK20, CODES!A:A,CODES!I:I)), "")
A21: Removed - Reassigned | B21: 2612 | C21: 183270 | D21: 46061 | E21: 5E22 | F21: 15:08 CRAIGNTNY to EDINBURGH | G21: XCN | H21: 24 | I21: 0 | J21: 24 | K21: 43 | L21: 0 | M21: 801226 | O21: 801226 | Q21: 9 | R21: 80x | S21: 43908 | T21: 5E22 24 LATE START XCN SET SWAP BETWEEN 1S12 TO FROM 1E20 & 1S09 TO FORM 1E21. REASON FOR SWAP WAS 801226 FITNESS TO RUN RAN OUT AT 22:26 SO HASD TO SWAP ONTO DIAGRAM SO COULD GET BACK BEFORE IT RAN OUT. SET SWAP SENT TO BOX 12:40 THEY SAID THEY CAN DO SWAP BUT 5E22 WOULD GET DELAY.AS COULD PUT INTO DIFFRENT PLATFORMS. TMV SHOWED AFTER 1E20 15:00 EDB-YRK DEPARTED PLATFORM 2 WAS AVAILABLE SO 5E22 SHOULD OFF LEFT CT AT 15:08AND DID NOT LEAVE UNTIL 15:25 & WENT INTO BOOKED PLATFORM 6. | U21: HRE Reject, MTIN – No. Depot report Unit held by the signaller awaiting platform space at Edinburgh Waverley. | V21: Details passed onto JP. JC 09/02 Comments required from FPPMs. JC 09/02 | W21: THBN | X21: THBN | Y21: TB | AA21: A | AB21: New | AC21: Investigation | AE21: 260208-183270 | AI21: =IF(AD21="Availability", 0, IF(AND(AE21="Y", OR(J21>2, L21>0)), 1, 0)) -> 0 | AJ21: 701B | AL21: =IFERROR(IF(AK21="", "", _xlfn.XLOOKUP(AK21, CODES!A:A,CODES!E:E)), "") | AM21: =IFERROR(IF(AK21="", "", _xlfn.XLOOKUP(AK21, CODES!A:A,CODES!G:G)), "") | AN21: =IFERROR(IF(AK21="", "", _xlfn.XLOOKUP(AK21, CODES!A:A,CODES!I:I)), "")
A22: Removed - Reassigned | B22: 2612 | C22: 182765 | D22: 46061 | E22: 1E07 | F22: 08:55 EDINBURGH to KINGS X Running as 08:55 EDINBURGH to YORK | G22: EDB | H22: 11 | I22: 0 | J22: 14 | K22: 30 | L22: 0 | M22: 801226 | O22: 801226 | Q22: 9 | R22: 80x | S22: 43908 | T22: 1E07 11 LATE START EDB SET WAS STABLED OVERNIGHT BUT IN THE MORNING HAD SIGNIFICANT ISSUE FIRST BUILDING UP AIR AND LATER THE PANTOGRAPH WAS UP BUT IT SHOWED BRAKE CONTROL FAULT WHICH DELAYED SERVICE IN DEPART EDB. LOG 260208-64 refers. | U22: HRE Reject, MTIN – No. Unit outstabled at EDB overnight in reaction to disruption 06/02. Low main res start up issues reported by the DVR. GU started to build air, Unit then auxed off to clear associated BCU faults one main res air pressure was established. | V22: Suspect low air start up issues. Drivers report requested - DR. JC 09/02 Details sent to JP, ops or driver issue. JC 09/02 Driver late to arrive, 08:37. JP moving to OPS standards. 10.02 S.B | W22: THBQ | X22: THBQ | Y22: TY | AA22: A | AB22: New | AC22: Referred | AE22: 260208-182765 | AG22: Rejected | AH22: N | AI22: =IF(AD22="Availability", 0, IF(AND(AE22="Y", OR(J22>2, L22>0)), 1, 0)) -> 0 | AJ22: 701B | AK22: 1AA | AL22: =IFERROR(IF(AK22="", "", _xlfn.XLOOKUP(AK22, CODES!A:A,CODES!E:E)), "") -> Operational | AM22: =IFERROR(IF(AK22="", "", _xlfn.XLOOKUP(AK22, CODES!A:A,CODES!G:G)), "") -> Staff | AN22: =IFERROR(IF(AK22="", "", _xlfn.XLOOKUP(AK22, CODES!A:A,CODES!I:I)), "") -> Driver | AO22: Unit outstabled over night at EDB. Low air start up issues.
A23: Removed - Reassigned | B23: 2612 | C23: 181742 | D23: 46060 | E23: 1S15 | F23: 12:03 KINGS X to INVERNES Running as 12:51 PETERBORO to INVERNES | G23: EDB | H23: 7 | I23: 0 | J23: 7 | K23: 14 | L23: 0 | M23: 801206 | O23: 801206 | Q23: 9 | R23: 80x | S23: 44013 | T23: 1S15 SET SWAP EDB 1S15 801206 SO REQUIRED A SET SWAP AT EDB WITH 5E25. 1S15 WILL FORM 1E25 EDB-PBO, 5E25 FORMED 1S15 EDB-INV. PLEASE MERGE WITH TIN 179043 DUE TO SET IMBALANCE DUE TO DEWIREMENT AT HAMBLETON 06.02.26. Swapped with 800106. LOG 260206-64 refers. | U23: HRE Reject, MTIN – No. 1S15 formed by 9ce vice 9cbi KGX - EDB in reaction to disruption 06/02/26 due to OHL damage. Unit 800106 swapped to form 1S15 EDB - ABD incurring a 7-minute delay. | V23: Merge requested. Jc 09/02 ADD event/ De-wirment 179043 | W23: THBN | X23: THBN | Y23: TB | AA23: A | AB23: New | AC23: Wtg_Att_Mgr_Dec | AE23: 260207-181742 | AG23: Rejected | AH23: N | AI23: =IF(AD23="Availability", 0, IF(AND(AE23="Y", OR(J23>2, L23>0)), 1, 0)) -> 0 | AJ23: 701B | AK23: 1DE | AL23: =IFERROR(IF(AK23="", "", _xlfn.XLOOKUP(AK23, CODES!A:A,CODES!E:E)), "") -> Operational | AM23: =IFERROR(IF(AK23="", "", _xlfn.XLOOKUP(AK23, CODES!A:A,CODES!G:G)), "") -> NR | AN23: =IFERROR(IF(AK23="", "", _xlfn.XLOOKUP(AK23, CODES!A:A,CODES!I:I)), "") -> Other | AO23: Set swap required at EDB following disruption from ADD event on 06/02.
A24: Root Cause | B24: 2612 | C24: 181387 | D24: 46060 | E24: 1A19 | F24: 11:37 Bradford Forster Square - Peterborough | G24: DON DONCLCJ | J24: 10 | K24: 17 | L24: 0 | M24: NL08 | N24: 91130 | O24: NL08 | Q24: 11 | R24: 225 | T24: 1A19 PANTO/AC DON DONCLCJ…..LOLL | U24: Lost line light | V24: WO 5088956 | W24: MHBA | X24: MHBA | Y24: M1 | AA24: A | AB24: New | AC24: Accepted | AE24: 260207-181387 | AH24: Y | AI24: =IF(AD24="Availability", 0, IF(AND(AE24="Y", OR(J24>2, L24>0)), 1, 0)) -> 0 | AJ24: 701D | AL24: =IFERROR(IF(AK24="", "", _xlfn.XLOOKUP(AK24, CODES!A:A,CODES!E:E)), "") | AM24: =IFERROR(IF(AK24="", "", _xlfn.XLOOKUP(AK24, CODES!A:A,CODES!G:G)), "") | AN24: =IFERROR(IF(AK24="", "", _xlfn.XLOOKUP(AK24, CODES!A:A,CODES!I:I)), "")
A25: Root Cause | B25: 2612 | C25: 180998 | D25: 46060 | E25: 3S08 | F25: 08:55 NEVHILL D to YORK | G25: XNL | H25: 7 | I25: 0 | J25: 7 | K25: 16 | L25: 0 | M25: 801222 | O25: 801222 | Q25: 9 | R25: 80x | S25: 43864 | T25: 3S08 7 LATE START XNL Unit late from depot, awaiting report. | U25: HRE Reject, MTIN – No. Depot report that the Driver did not ring to advise that they were ready to depart until 09:00 (booked departure 08:55). Class 3 only delay. | V25: Drivers report requested - JM. JC 09/02 Depot process delay. JC 13/02 | W25: MHBM | X25: MHBM | Y25: MU | AA25: A | AB25: New | AC25: Accepted | AE25: 260207-180998 | AG25: Rejected - Class 3/5 | AH25: N | AI25: =IF(AD25="Availability", 0, IF(AND(AE25="Y", OR(J25>2, L25>0)), 1, 0)) -> 0 | AJ25: 701A | AK25: 1BD | AL25: =IFERROR(IF(AK25="", "", _xlfn.XLOOKUP(AK25, CODES!A:A,CODES!E:E)), "") -> Operational | AM25: =IFERROR(IF(AK25="", "", _xlfn.XLOOKUP(AK25, CODES!A:A,CODES!G:G)), "") -> Depot | AN25: =IFERROR(IF(AK25="", "", _xlfn.XLOOKUP(AK25, CODES!A:A,CODES!I:I)), "") -> Process | AO25: Unit late off depot.
A26: Check - not on Fleet Attr | B26: 2612 | C26: 180628 | D26: 46060 | G26: XNL | J26: 6 | K26: 6 | L26: 0 | M26: NL08 | O26: NL08 | Q26: 11 | R26: 225 | T26: 5A05 6 LATE START XNL | U26: Following late departure | V26: Following late departure | W26: MHBM | X26: MHBM | Y26: MU | AA26: D | AB26: New | AC26: Investigation | AE26: 260207-180628 | AH26: N | AI26: =IF(AD26="Availability", 0, IF(AND(AE26="Y", OR(J26>2, L26>0)), 1, 0)) -> 0 | AJ26: 701A | AL26: =IFERROR(IF(AK26="", "", _xlfn.XLOOKUP(AK26, CODES!A:A,CODES!E:E)), "") | AM26: =IFERROR(IF(AK26="", "", _xlfn.XLOOKUP(AK26, CODES!A:A,CODES!G:G)), "") | AN26: =IFERROR(IF(AK26="", "", _xlfn.XLOOKUP(AK26, CODES!A:A,CODES!I:I)), "")
A27: Removed - Reassigned | B27: 2612 | C27: 179769 | D27: 46059 | E27: 1S19 | F27: 14:03 KINGS X to ABERDEEN | G27: YRK | H27: 4 | I27: 0 | J27: 4 | K27: 4 | L27: 0 | M27: 800105 | N27: 819105 | O27: 800105 | Q27: 9 | R27: 80x | S27: 43572 | T27: 1S19 PANTO YRK Raising pan in platform, suspect unit operating in diesel following ADD event. | U27: HRE Reject, MTIN – No. Quartz report states TM checking whether they were supposed to be issued an SSO for NTR at York (York staff had not been asked to do this) & volume of passengers due to disruption caused by OHL damage. | V27: Drivers report requested - AAB. JC 09/02 TM report requested - HM. JC 09/02 Drvier reports passenger loadings, details sent onto JP. JC 11/02 | W27: THBN | X27: THBN | Y27: TP | AA27: A | AB27: New | AC27: Wtg_Att_Mgr_Dec | AE27: 260206-179769 | AG27: Rejected | AH27: N | AI27: =IF(AD27="Availability", 0, IF(AND(AE27="Y", OR(J27>2, L27>0)), 1, 0)) -> 0 | AJ27: 701B | AK27: 1AB | AL27: =IFERROR(IF(AK27="", "", _xlfn.XLOOKUP(AK27, CODES!A:A,CODES!E:E)), "") -> Operational | AM27: =IFERROR(IF(AK27="", "", _xlfn.XLOOKUP(AK27, CODES!A:A,CODES!G:G)), "") -> Staff | AN27: =IFERROR(IF(AK27="", "", _xlfn.XLOOKUP(AK27, CODES!A:A,CODES!I:I)), "") -> TM | AO27: TM checking whether they were supposed to be issued an SSO for NTR at York
A28: Root Cause, Bugle Dispute Status | B28: 2612 | C28: 179509 | D28: 46059 | E28: 1A30 | F28: 17:40 LEEDS to KINGS X | G28: LEEDS | H28: 0 | I28: 1 | J28: 0 | K28: 0 | L28: 1 | M28: 800111 | N28: 818111 | O28: 800111 | Q28: 9 | R28: 80x | S28: 43532 | T28: 1A30 FITTERS ATTENTION LDS From min braking to max moving the CPBC brake pressure don't rise along with the CPBC until nearly into max and then BCP pressures rise. Driver not happy with the issue and not taking unit due to potential passing a signal if pressure are not rising. TRI in attendance. Possible LAD10 card issue. LOG 260206-78 refers. SAP 8339327 refers - | U28: Under investigation. | V28: Drivers report requested - JM. JC 09/02 | W28: MHB1 | X28: MHB1 | Y28: MN | Z28: MN | AA28: A | AB28: Accepted | AC28: Investigation | AE28: 260206-179509 | AG28: Investigation | AI28: =IF(AD28="Availability", 0, IF(AND(AE28="Y", OR(J28>2, L28>0)), 1, 0)) -> 0 | AJ28: 701D | AL28: =IFERROR(IF(AK28="", "", _xlfn.XLOOKUP(AK28, CODES!A:A,CODES!E:E)), "") | AM28: =IFERROR(IF(AK28="", "", _xlfn.XLOOKUP(AK28, CODES!A:A,CODES!G:G)), "") | AN28: =IFERROR(IF(AK28="", "", _xlfn.XLOOKUP(AK28, CODES!A:A,CODES!I:I)), "")
A29: Root Cause | B29: 2612 | C29: 179324 | D29: 46059 | E29: 1D20 | F29: 15:10 London Kings Cross - Leeds | G29: KNGXBEL | J29: 5 | K29: 5 | L29: 0 | M29: NL06 | O29: NL06 | Q29: 11 | R29: 225 | T29: 1D20 BRAKES KNGXBEL | W29: MHBA | X29: MHBA | Y29: MN | AA29: A | AB29: New | AC29: Investigation | AE29: 260206-179324 | AI29: =IF(AD29="Availability", 0, IF(AND(AE29="Y", OR(J29>2, L29>0)), 1, 0)) -> 0 | AJ29: 701D | AL29: =IFERROR(IF(AK29="", "", _xlfn.XLOOKUP(AK29, CODES!A:A,CODES!E:E)), "") | AM29: =IFERROR(IF(AK29="", "", _xlfn.XLOOKUP(AK29, CODES!A:A,CODES!G:G)), "") | AN29: =IFERROR(IF(AK29="", "", _xlfn.XLOOKUP(AK29, CODES!A:A,CODES!I:I)), "")
A30: Removed | B30: 2612 | C30: 178518 | D30: 46059 | F30: 09:14 CRAIGNTNY to EDINBURGH | G30: XCN | H30: 5 | I30: 0 | J30: 5 | K30: 5 | L30: 0 | M30: 801220 | O30: 801220 | Q30: 9 | R30: 80x | S30: 43852 | T30: 5E10 LATE START XCN TMV REPLAY SHOWS 5Z56 ROUTED INTO XCN DEPOT, PREVENTING RT DEPARTURE OF 5E10. | U30: HRE Reject, MTIN – No. Depot report 5E10 delayed due to 5Z00 arriving from the mainline. Class 5 only delay. | V30: Details passed onto JP. Jc 09/02 Incident has been removed and merged to Scotrail. 10/02 S.B | W30: MHBK | X30: MHBK | Y30: MU | AA30: D | AB30: New | AC30: Referred | AE30: 260206-178518 | AG30: Rejected - Class 3/5 | AH30: N | AI30: =IF(AD30="Availability", 0, IF(AND(AE30="Y", OR(J30>2, L30>0)), 1, 0)) -> 0 | AJ30: 701A | AK30: 1DB | AL30: =IFERROR(IF(AK30="", "", _xlfn.XLOOKUP(AK30, CODES!A:A,CODES!E:E)), "") -> Operational | AM30: =IFERROR(IF(AK30="", "", _xlfn.XLOOKUP(AK30, CODES!A:A,CODES!G:G)), "") -> NR | AN30: =IFERROR(IF(AK30="", "", _xlfn.XLOOKUP(AK30, CODES!A:A,CODES!I:I)), "") -> Regulation | AO30: Unit late off depot.
A31: Root Cause | B31: 2612 | C31: 178432 | D31: 46059 | E31: 1E03 | F31: 06:30 EDINBURGH to KINGS X | G31: NCL KEBGSJN | H31: 2 | I31: 0 | J31: 2 | K31: 2 | L31: 0 | M31: 801223 | N31: 828223 | O31: 801223 | Q31: 9 | R31: 80x | S31: 43896 | T31: 1E03 2 LOST NCL KEBGSJN 1E03 TO DEPART NCL VIA HLB TO PUT SET IN REVERSE, REQUIRED BY HITACHI TO FIX THE TRACTION CONVERTER. SAP 8292796 refers. | U31: Sub threshold delay. CPC request for Unit to be turned at Newcastle and into reverse formation for EOD maintenance requirements at DON IEP (K1 - 801223 Traction Converter reps & RUX001 (DON). | V31: Email sent to JP to change to 701A - MS. Jc 09/02 | W31: MHB2 | X31: MHB2 | Y31: MD | AA31: A | AB31: New | AC31: Accepted | AE31: 260206-178432 | AG31: Rejected - Sub Threshold | AH31: N | AI31: =IF(AD31="Availability", 0, IF(AND(AE31="Y", OR(J31>2, L31>0)), 1, 0)) -> 0 | AJ31: 701D | AK31: 1CC | AL31: =IFERROR(IF(AK31="", "", _xlfn.XLOOKUP(AK31, CODES!A:A,CODES!E:E)), "") -> Operational | AM31: =IFERROR(IF(AK31="", "", _xlfn.XLOOKUP(AK31, CODES!A:A,CODES!G:G)), "") -> Control | AN31: =IFERROR(IF(AK31="", "", _xlfn.XLOOKUP(AK31, CODES!A:A,CODES!I:I)), "") -> HRL CPC | AO31: Unit turned at Newcastle for EoD maintenance requirements.
A32: Root Cause, Bugle Dispute Status | B32: 2612 | C32: 177745 | D32: 46059 | E32: 1E10 | F32: 10:00 EDINBURGH to KINGS X | G32: EDB | H32: 0 | I32: 1 | J32: 0 | K32: 5 | L32: 1 | M32: 801220 | N32: 824220 | O32: 801220 | Q32: 9 | R32: 80x | S32: 43852 | T32: 1E10 CANCELLED EDB HFMC advises that a pest has been seen on the train. HFMC have asked if traps can be put down and advise set in service on 06/02. STSM has asked what kind of traps will be used and clarification to be given regarding this issue. Cannot swap set out as nothing available at Craigentinny. HFMC advise that Rentokil have not answered the message. Waiting to here back from HFMC as they are due to have a meeting shortly with Depot staff on updates of sets. LOG 260206-10 refers. SAP 8334663 refers. | U32: HRE Reject, MTIN – No. Unit 801220 not available for service due to the ongoing investigation into reports of a mouse in vehicle 824220 reported whilst working as 1S25 on the 05/02. In reaction, 1E10 cancelled. Covered under Availability. | W32: MHB2 | X32: MHB2 | Y32: MS | Z32: MS | AA32: A | AB32: Accepted | AC32: Accepted | AE32: 260206-177745 | AG32: Availability | AH32: N | AI32: =IF(AD32="Availability", 0, IF(AND(AE32="Y", OR(J32>2, L32>0)), 1, 0)) -> 0 | AJ32: 701A | AK32: 2BD | AL32: =IFERROR(IF(AK32="", "", _xlfn.XLOOKUP(AK32, CODES!A:A,CODES!E:E)), "") -> LNER | AM32: =IFERROR(IF(AK32="", "", _xlfn.XLOOKUP(AK32, CODES!A:A,CODES!G:G)), "") -> Other | AN32: =IFERROR(IF(AK32="", "", _xlfn.XLOOKUP(AK32, CODES!A:A,CODES!I:I)), "") -> Availability | AO32: Unit 801220 not available for service due to the ongoing investigation into reports of a mouse in vehicle 824220 reported whilst working as 1S25 on the 05/02.
A33: Root Cause | B33: 2612 | C33: 177582 | D33: 46059 | E33: 5Y23 | F33: 21:22 KINGS X to BOUNDGNCS | G33: FERMEPK | H33: 44 | I33: 0 | J33: 44 | K33: 44 | L33: 0 | M33: 801108/01 | O33: 801108 | P33: 801101 | Q33: 5 | R33: 80x | S33: 43700 | T33: 5Y23 DEPOT OPS FERMEPK 05/02 DEPOT OPS FEREM PARK | U33: HRE Reject, MTIN – No. Waiting acceptance onto Bounds Green. Depot report 5Y23 was 45 minutes late off the wash road due to 5Y86 being processed ahead and then waiting for a road onto the Depot. Class 5 only delay. | W33: MHBJ | X33: MHBJ | Y33: MU | Z33: MU | AA33: A | AB33: Accepted | AC33: Accepted | AE33: 260206-177582 | AG33: Rejected - Class 3/5 | AH33: N | AI33: =IF(AD33="Availability", 0, IF(AND(AE33="Y", OR(J33>2, L33>0)), 1, 0)) -> 0 | AJ33: 701A | AK33: 1BD | AL33: =IFERROR(IF(AK33="", "", _xlfn.XLOOKUP(AK33, CODES!A:A,CODES!E:E)), "") -> Operational | AM33: =IFERROR(IF(AK33="", "", _xlfn.XLOOKUP(AK33, CODES!A:A,CODES!G:G)), "") -> Depot | AN33: =IFERROR(IF(AK33="", "", _xlfn.XLOOKUP(AK33, CODES!A:A,CODES!I:I)), "") -> Process | AO33: Unit late onto depot.
A34: Root Cause | B34: 2612 | C34: 176963 | D34: 46058 | E34: 1E25 | F34: 14:52 ABERDEEN to KINGS X | G34: KDY INK | H34: 2 | I34: 0 | J34: 2 | K34: 2 | L34: 0 | M34: 800105 | O34: 800105 | Q34: 9 | R34: 80x | S34: 43572 | T34: 1E25 2 LOST KDY INK Adhesion. | U34: Sub threshold delay. | W34: MHB1 | X34: MHB1 | Y34: MP | AA34: A | AB34: New | AC34: Accepted | AE34: 260205-176963 | AG34: Rejected - Sub Threshold | AH34: N | AI34: =IF(AD34="Availability", 0, IF(AND(AE34="Y", OR(J34>2, L34>0)), 1, 0)) -> 0 | AJ34: 750 | AK34: 2BE | AL34: =IFERROR(IF(AK34="", "", _xlfn.XLOOKUP(AK34, CODES!A:A,CODES!E:E)), "") -> LNER | AM34: =IFERROR(IF(AK34="", "", _xlfn.XLOOKUP(AK34, CODES!A:A,CODES!G:G)), "") -> Other | AN34: =IFERROR(IF(AK34="", "", _xlfn.XLOOKUP(AK34, CODES!A:A,CODES!I:I)), "") -> Adhesion | AO34: Adhesion.
A35: Removed - Reassigned | B35: 2612 | C35: 176917 | D35: 46058 | E35: 1S24 | F35: 16:30 KINGS X to EDINBURGH | G35: YRK | H35: 3 | I35: 0 | J35: 3 | K35: 3 | L35: 0 | M35: 801209 | N35: 829209 | O35: 801209 | Q35: 9 | R35: 80x | S35: 43791 | T35: 1S24 3 OVERTIME YRK Door B in Coach M has LOOU. LOG 260205-75 refers. SAP 8331983 refers - Door B LOOU. | U35: Further details required please. Quartz states Customer in a wheelchair needing to board the service, door in M out of use and couldn’t use door in L as expected. Had to board customer in A instead and bring the lady to the front of the train from the rear. No active door faults raised in SAP or recorded in the HMC Log. MTIN NO, HRE REJECT - As discussed, a route message was sent out at 13:53 advising that Door B of 829209 was LOOU. It appears that this was not managed correctly in service resulting in an avoidable delay at York. | V35: Door appears to have been LOOU on 3S02 leaving leeds. Awaiting TM report from AAB. JM has provided details on it. JC 06/02 AAB has reported back. Details sent onto CPT. JC 12/02 referral request sent to LJ at York. JC 12/02 | W35: RHBK | X35: RHBK | Y35: RC | AA35: A | AB35: New | AC35: Referred | AE35: 260205-176917 | AG35: Rejected | AH35: N | AI35: =IF(AD35="Availability", 0, IF(AND(AE35="Y", OR(J35>2, L35>0)), 1, 0)) -> 0 | AJ35: 701E | AK35: 1AD | AL35: =IFERROR(IF(AK35="", "", _xlfn.XLOOKUP(AK35, CODES!A:A,CODES!E:E)), "") -> Operational | AM35: =IFERROR(IF(AK35="", "", _xlfn.XLOOKUP(AK35, CODES!A:A,CODES!G:G)), "") -> Staff | AN35: =IFERROR(IF(AK35="", "", _xlfn.XLOOKUP(AK35, CODES!A:A,CODES!I:I)), "") -> Platform | AO35: Route message not adhered to.
A36: Root Cause | B36: 2612 | C36: 176008 | D36: 46058 | E36: 1S05 | F36: 07:03 KINGS X to EDINBURGH | G36: BELFORD BWK | H36: 4 | I36: 0 | J36: 4 | K36: 11 | L36: 0 | M36: 801218 | N36: 825218 | O36: 801218 | Q36: 9 | R36: 80x | S36: 43998 | T36: 1S05 4 LOST BELFORD BWK TMS 4045 VCB2(3) Close Failure SAP 8337507 refers. | U36: Under investigation. | W36: MHB2 | X36: MHB2 | Y36: MD | AA36: A | AB36: New | AC36: Investigation | AE36: 260205-176008 | AG36: Investigation | AI36: =IF(AD36="Availability", 0, IF(AND(AE36="Y", OR(J36>2, L36>0)), 1, 0)) -> 0 | AJ36: 701D | AL36: =IFERROR(IF(AK36="", "", _xlfn.XLOOKUP(AK36, CODES!A:A,CODES!E:E)), "") | AM36: =IFERROR(IF(AK36="", "", _xlfn.XLOOKUP(AK36, CODES!A:A,CODES!G:G)), "") | AN36: =IFERROR(IF(AK36="", "", _xlfn.XLOOKUP(AK36, CODES!A:A,CODES!I:I)), "")
A37: Root Cause | B37: 2612 | C37: 175515 | D37: 46058 | E37: 1S04 | F37: 06:30 KINGS X to EDINBURG | G37: NNG RET | H37: 6 | I37: 0 | J37: 6 | K37: 6 | L37: 0 | M37: 801207 | N37: 825207 | O37: 801207 | Q37: 9 | R37: 80x | S37: 43783 | T37: 1S04 3 LOST NNG RET TMS 0637 Door B Open while Running. LOG 260205-56 refers. SAP 8337306 refers - slight adjustment carried out to DCS. | U37: MTIN YES, HRE ACCEPT - DCS (old type) to be replaced. | W37: MHB2 | X37: MHB2 | Y37: M7 | Z37: M7 | AA37: A | AB37: Accepted | AC37: Accepted | AE37: 260205-175515 | AG37: Accepted | AH37: Y | AI37: =IF(AD37="Availability", 0, IF(AND(AE37="Y", OR(J37>2, L37>0)), 1, 0)) -> 0 | AJ37: 701D | AK37: OBD | AL37: =IFERROR(IF(AK37="", "", _xlfn.XLOOKUP(AK37, CODES!A:A,CODES!E:E)), "") -> Doors | AM37: =IFERROR(IF(AK37="", "", _xlfn.XLOOKUP(AK37, CODES!A:A,CODES!G:G)), "") -> Exterior Passenger Doors | AN37: =IFERROR(IF(AK37="", "", _xlfn.XLOOKUP(AK37, CODES!A:A,CODES!I:I)), "") -> Door Close Switch (DCS) | AO37: TMS 0637 Door B Open while Running, old DCS to be replaced.
A38: Check - not on Fleet Attr | B38: 2612 | C38: 175190 | D38: 46058 | F38: 05:35 Neville Hill T&R.S.M.D - Leeds | G38: XNL | J38: 4 | K38: 4 | L38: 0 | M38: NL12 | O38: NL12 | Q38: 11 | R38: 225 | T38: 5A05 4 LATE START XNL | U38: Waiting signals | W38: MHBM | X38: MHBM | Y38: MU | AA38: D | AB38: New | AC38: Investigation | AE38: 260205-175190 | AH38: N | AI38: =IF(AD38="Availability", 0, IF(AND(AE38="Y", OR(J38>2, L38>0)), 1, 0)) -> 0 | AJ38: 701A | AL38: =IFERROR(IF(AK38="", "", _xlfn.XLOOKUP(AK38, CODES!A:A,CODES!E:E)), "") | AM38: =IFERROR(IF(AK38="", "", _xlfn.XLOOKUP(AK38, CODES!A:A,CODES!G:G)), "") | AN38: =IFERROR(IF(AK38="", "", _xlfn.XLOOKUP(AK38, CODES!A:A,CODES!I:I)), "")
A39: Root Cause | B39: 2612 | C39: 173841 | D39: 46057 | E39: 1A24 | F39: 14:40 Leeds - London Kings Cross | G39: AWK DON | J39: 14 | K39: 23 | L39: 0 | M39: NL26 | N39: 91110 | O39: NL26 | Q39: 11 | R39: 225 | T39: 1A24 3 LOST AWK DON | U39: General fault light lit | V39: WO 5088912 MPU shows No1 bogie overload | W39: MHBA | X39: MHBA | Y39: M1 | Z39: M1 | AA39: A | AB39: Accepted | AC39: Accepted | AE39: 260204-173841 | AH39: Y | AI39: =IF(AD39="Availability", 0, IF(AND(AE39="Y", OR(J39>2, L39>0)), 1, 0)) -> 0 | AJ39: 701D | AL39: =IFERROR(IF(AK39="", "", _xlfn.XLOOKUP(AK39, CODES!A:A,CODES!E:E)), "") | AM39: =IFERROR(IF(AK39="", "", _xlfn.XLOOKUP(AK39, CODES!A:A,CODES!G:G)), "") | AN39: =IFERROR(IF(AK39="", "", _xlfn.XLOOKUP(AK39, CODES!A:A,CODES!I:I)), "")
A40: Root Cause | B40: 2612 | C40: 172843 | D40: 46057 | E40: 3A13 | F40: 07:12 NEVHILL D to HARROGATE | G40: XNL | H40: 11 | I40: 0 | J40: 11 | K40: 11 | L40: 0 | M40: 800101 | O40: 800101 | Q40: 9 | R40: 80x | S40: 43920 | T40: 3A13 11 LATE START XNL DEPOT REPORT DELAYED FOLLOWING LATE 3Y06. AS ON DEPOT, EACH OPERATOR TAKES OWN DELAY. | U40: HRE Reject, MTIN – No. Depot report 3A13 delayed following late departing 3Y06, which was delayed due to the Driver arriving late. Class 3 only delay. | W40: MHBM | X40: MHBM | Y40: MU | AA40: A | AB40: New | AC40: Accepted | AE40: 260204-172843 | AG40: Rejected - Class 3/5 | AH40: N | AI40: =IF(AD40="Availability", 0, IF(AND(AE40="Y", OR(J40>2, L40>0)), 1, 0)) -> 0 | AJ40: 701A | AK40: 1BD | AL40: =IFERROR(IF(AK40="", "", _xlfn.XLOOKUP(AK40, CODES!A:A,CODES!E:E)), "") -> Operational | AM40: =IFERROR(IF(AK40="", "", _xlfn.XLOOKUP(AK40, CODES!A:A,CODES!G:G)), "") -> Depot | AN40: =IFERROR(IF(AK40="", "", _xlfn.XLOOKUP(AK40, CODES!A:A,CODES!I:I)), "") -> Process | AO40: Unit late off depot.
A41: Root Cause | B41: 2612 | C41: 172613 | D41: 46057 | E41: 3Y81 | F41: 05:34 HEATON CS to MIDDLSBRO | G41: XHT | H41: 21 | I41: 0.5 | J41: 21 | K41: 33 | L41: 0 | M41: 800209 | O41: 800209 | Q41: 5 | R41: 80x | S41: 43805 | T41: 3Y81 21 LATE START XHT Awaiting depot report. Late start to 1Y81 - 9 minutes. | U41: MTIN – No, HRE Accept responsibility for the 9 minute late start of 1Y81. Depot report overrunning maintenance/exam work. | V41: Quartz reports: late off maintenance | W41: MHBN | X41: MHBN | Y41: MU | Z41: MU | AA41: A | AB41: Accepted | AC41: Accepted | AE41: 260204-172613 | AG41: Accepted | AH41: N | AI41: =IF(AD41="Availability", 0, IF(AND(AE41="Y", OR(J41>2, L41>0)), 1, 0)) -> 0 | AJ41: 701A | AK41: 1BD | AL41: =IFERROR(IF(AK41="", "", _xlfn.XLOOKUP(AK41, CODES!A:A,CODES!E:E)), "") -> Operational | AM41: =IFERROR(IF(AK41="", "", _xlfn.XLOOKUP(AK41, CODES!A:A,CODES!G:G)), "") -> Depot | AN41: =IFERROR(IF(AK41="", "", _xlfn.XLOOKUP(AK41, CODES!A:A,CODES!I:I)), "") -> Process | AO41: Unit late off depot.
A42: Root Cause | B42: 2612 | C42: 171340 | D42: 46056 | E42: 1S21 | F42: 15:03 KINGS X to EDINBURGH | G42: DONCLCJ DON | H42: 3 | I42: 0 | J42: 3 | K42: 9 | L42: 0 | M42: 801207 | O42: 801207 | Q42: 9 | R42: 80x | S42: 43783 | T42: 1S21 3 LOST DONCLCJ DON Adhesion. | U42: MTIN NO, HRE REJECT - Reported adhesion issues. | W42: MHB2 | X42: MHB2 | Y42: MP | Z42: MP | AA42: A | AB42: Accepted | AC42: Accepted | AE42: 260203-171340 | AG42: Rejected | AH42: N | AI42: =IF(AD42="Availability", 0, IF(AND(AE42="Y", OR(J42>2, L42>0)), 1, 0)) -> 0 | AJ42: 750 | AK42: 2BE | AL42: =IFERROR(IF(AK42="", "", _xlfn.XLOOKUP(AK42, CODES!A:A,CODES!E:E)), "") -> LNER | AM42: =IFERROR(IF(AK42="", "", _xlfn.XLOOKUP(AK42, CODES!A:A,CODES!G:G)), "") -> Other | AN42: =IFERROR(IF(AK42="", "", _xlfn.XLOOKUP(AK42, CODES!A:A,CODES!I:I)), "") -> Adhesion | AO42: Adhesion
A43: Root Cause | B43: 2612 | C43: 170578 | D43: 46056 | E43: 1Y10 | F43: 09:27 NCASTLCEN to KINGS X | G43: NTR THI | H43: 21 | I43: 0 | J43: 21 | K43: 43 | L43: 0 | M43: 801106 | N43: 821106 | O43: 801106 | Q43: 5 | R43: 80x | S43: 43700 | T43: 1Y10 21 LOST NTR THI TMS 6602 No Current from the OHL reported by driver. LOG 260203-61 refers. SAP 8334665 refers. | U43: HRE Reject, MTIN – No. Confirmed OHL Low Voltage. Please see the report attached for further details. | V43: Dispute raised. CCTV Requested. JC 04/02 AJ contacted for details on Pan checks and the FFG to aid dispute. JC 04/02 CCTV hopeless. JC 09/02 | W43: MHB2 | X43: MHB2 | Y43: M1 | AA43: D | AB43: New | AC43: Investigation | AE43: 260203-170578 | AG43: Rejected | AH43: N | AI43: =IF(AD43="Availability", 0, IF(AND(AE43="Y", OR(J43>2, L43>0)), 1, 0)) -> 0 | AJ43: 701D | AK43: 1DA | AL43: =IFERROR(IF(AK43="", "", _xlfn.XLOOKUP(AK43, CODES!A:A,CODES!E:E)), "") -> Operational | AM43: =IFERROR(IF(AK43="", "", _xlfn.XLOOKUP(AK43, CODES!A:A,CODES!G:G)), "") -> NR | AN43: =IFERROR(IF(AK43="", "", _xlfn.XLOOKUP(AK43, CODES!A:A,CODES!I:I)), "") -> OHL | AO43: Low voltage detected by unit causing 6602 event.
A44: Root Cause | B44: 2612 | C44: 169891 | D44: 46056 | E44: 5A05 | F44: 05:35 Neville Hill T&R.S.M.D - Leeds | G44: XNL | J44: 14 | K44: 14 | L44: 0 | M44: NL06 | O44: NL06 | Q44: 11 | R44: 225 | T44: 5A05 14 LATE START XNL | U44: Late off servicing due to a possession | W44: MHBM | X44: MHBM | Y44: MU | AA44: A | AB44: New | AC44: Accepted | AE44: 260203-169891 | AH44: N | AI44: =IF(AD44="Availability", 0, IF(AND(AE44="Y", OR(J44>2, L44>0)), 1, 0)) -> 0 | AJ44: 701A | AL44: =IFERROR(IF(AK44="", "", _xlfn.XLOOKUP(AK44, CODES!A:A,CODES!E:E)), "") | AM44: =IFERROR(IF(AK44="", "", _xlfn.XLOOKUP(AK44, CODES!A:A,CODES!G:G)), "") | AN44: =IFERROR(IF(AK44="", "", _xlfn.XLOOKUP(AK44, CODES!A:A,CODES!I:I)), "")
A45: Root Cause | B45: 2612 | C45: 169595 | D45: 46056 | E45: 1S32 | F45: 20:03 KINGS X to EDINBURGH | G45: GRA NNG | H45: 2 | I45: 0 | J45: 2 | K45: 2 | L45: 0 | M45: 801205 | N45: 825205 | O45: 801205 | Q45: 9 | R45: 80x | S45: 43782 | T45: 1S32 2 LOST GRA NNG 02/02 TC ISOLATED, DRIVER REPORTS SLOW TO LINE SPEED. | U45: MTIN NO, HRE REJECT | W45: MHB2 | X45: MHB2 | Y45: MD | AA45: A | AB45: Pending | AC45: Accepted | AE45: 260203-169595 | AG45: Rejected - Sub Threshold | AH45: N | AI45: =IF(AD45="Availability", 0, IF(AND(AE45="Y", OR(J45>2, L45>0)), 1, 0)) -> 0 | AJ45: 701D | AK45: PH6 | AL45: =IFERROR(IF(AK45="", "", _xlfn.XLOOKUP(AK45, CODES!A:A,CODES!E:E)), "") -> Traction and Power Equipment | AM45: =IFERROR(IF(AK45="", "", _xlfn.XLOOKUP(AK45, CODES!A:A,CODES!G:G)), "") -> Traction Converter | AN45: =IFERROR(IF(AK45="", "", _xlfn.XLOOKUP(AK45, CODES!A:A,CODES!I:I)), "") -> Fault not Investigated | AO45: Time lost in running, TC isoalted on 825 car.
A46: Removed - Reassigned | B46: 2612 | C46: 168684 | D46: 46055 | E46: 1N09 | F46: 14:33 KINGS X to NCASTLCEN | G46: TOLERTN THI | H46: 54 | I46: 0 | J46: 105 | K46: 188 | L46: 0 | M46: 800110 | N46: 817110 | O46: 800110 | Q46: 9 | R46: 80x | S46: 43584 | T46: 1N09 51 LOST TOLERTN THI Sparking from underneath vehicle 7, suspected AIVR equipment lights. **AIVR is installed on car 6** LOG 260202-49 refers. SAP 8333696 refers. | U46: MTIN NO, HRE REJECT - NFF/ safety of the line incident. Train found to have NR AVIR equipment fitted to the underframe on that vehicle which operates a strobe light bar of LEDS for track monitoring equipment. | V46: Referral request sent to LNER Control. JC 03/02 | W46: THBQ | X46: THBQ | Y46: TY | Z46: TY | AA46: A | AB46: Accepted | AC46: Referred | AE46: 260202-168684 | AG46: Rejected | AH46: N | AI46: =IF(AD46="Availability", 0, IF(AND(AE46="Y", OR(J46>2, L46>0)), 1, 0)) -> 0 | AJ46: 701B | AK46: 1CA | AL46: =IFERROR(IF(AK46="", "", _xlfn.XLOOKUP(AK46, CODES!A:A,CODES!E:E)), "") -> Operational | AM46: =IFERROR(IF(AK46="", "", _xlfn.XLOOKUP(AK46, CODES!A:A,CODES!G:G)), "") -> Control | AN46: =IFERROR(IF(AK46="", "", _xlfn.XLOOKUP(AK46, CODES!A:A,CODES!I:I)), "") -> LNER | AO46: SDT appear to not have read brief regarding AIVR installation.
A47: Root Cause | B47: 2612 | C47: 168514 | D47: 46055 | E47: 1A22 | F47: 13:40 LEEDS to KINGS X | G47: PBO | H47: 3 | I47: 0 | J47: 3 | K47: 3 | L47: 0 | M47: 801221 | N47: 827221 | O47: 801221 | Q47: 9 | R47: 80x | S47: 43859 | T47: 1A22 3 OVERTIME PBO COACH K DOOR A LOCKED OUT OF USE. SAP 8333576 refers - Door A Bouncing Open. | U47: MTIN NO, HRE REJECT - Luggage wheel found lodged in the Door runner. Please see the report attached. | W47: MHBV | X47: MHBV | Y47: MF | AA47: A | AB47: New | AC47: Accepted | AE47: 260202-168514 | AG47: Rejected | AH47: N | AI47: =IF(AD47="Availability", 0, IF(AND(AE47="Y", OR(J47>2, L47>0)), 1, 0)) -> 0 | AJ47: 701A | AK47: 2BF | AL47: =IFERROR(IF(AK47="", "", _xlfn.XLOOKUP(AK47, CODES!A:A,CODES!E:E)), "") -> LNER | AM47: =IFERROR(IF(AK47="", "", _xlfn.XLOOKUP(AK47, CODES!A:A,CODES!G:G)), "") -> Other | AN47: =IFERROR(IF(AK47="", "", _xlfn.XLOOKUP(AK47, CODES!A:A,CODES!I:I)), "") -> Cleaning | AO47: Suspected debris in the door runner.
A48: Root Cause | B48: 2612 | C48: 168071 | D48: 46055 | E48: 1D03 | F48: 06:40 KINGS X to HARROGATE | G48: N/A | H48: 0 | I48: 0.5 | J48: 0 | K48: 0 | L48: 1.5 | M48: 800104 | O48: 801205 | Q48: 9 | R48: 80x | S48: 43782 | T48: 1D03 CANCELLED LDS HGT 30/01 1D03 0640 Kings Cross to Harrogate will terminate at Leeds (reaction to broken windscreen on 800104) $TSDB! - Set will run ECS to Neville Hill before returning for 1A17. Electric vice Bi. LOG 260130-8 refers. | U48: MTIN NO, HRE REJECT - Covered under availability. | W48: MHB1 | X48: MHB1 | Y48: MS | AA48: A | AB48: New | AC48: Accepted | AE48: 260202-168071 | AG48: Availability | AH48: N | AI48: =IF(AD48="Availability", 0, IF(AND(AE48="Y", OR(J48>2, L48>0)), 1, 0)) -> 0 | AJ48: 701A | AK48: 2BD | AL48: =IFERROR(IF(AK48="", "", _xlfn.XLOOKUP(AK48, CODES!A:A,CODES!E:E)), "") -> LNER | AM48: =IFERROR(IF(AK48="", "", _xlfn.XLOOKUP(AK48, CODES!A:A,CODES!G:G)), "") -> Other | AN48: =IFERROR(IF(AK48="", "", _xlfn.XLOOKUP(AK48, CODES!A:A,CODES!I:I)), "") -> Availability | AO48: Electric vice Bi owing to broken windscreen on 800104.
A49: Removed | B49: 2611 | C49: 164816 | D49: 46053 | F49: 16:27 NCASTLCEN to PETERBORO | G49: NCL | H49: 23 | I49: 0 | J49: 23 | K49: 42 | L49: 0 | M49: 801218 | O49: 801218 | Q49: 9 | R49: 80x | S49: 43998 | T49: 1Y18 23 LATE START NCL QUARTZ REPORT SUGGESTS TRAIN WAS LATE ARRIVING FROM DEPOT. Presented from depot at 16:36:52 from Heaton. | U49: HRE Reject, MTIN – No. Late departure from Newcastle. Inward 5Y18 delayed from Heaton awaiting the Driver after a miscommunication withing the LNER SDT resulting in no Driver being allocated for 5Y18 Heaton - Newcastle. LNER Log 260131-50 refers. | V49: TMV checked. JC 02/02 Details passed onto JP. JC 02/02 | W49: MHBN | X49: MHBN | Y49: MU | AA49: D | AB49: New | AC49: Referred | AE49: 260131-164816 | AG49: Rejected | AH49: N | AI49: =IF(AD49="Availability", 0, IF(AND(AE49="Y", OR(J49>2, L49>0)), 1, 0)) -> 0 | AJ49: 701A | AK49: 1CA | AL49: =IFERROR(IF(AK49="", "", _xlfn.XLOOKUP(AK49, CODES!A:A,CODES!E:E)), "") -> Operational | AM49: =IFERROR(IF(AK49="", "", _xlfn.XLOOKUP(AK49, CODES!A:A,CODES!G:G)), "") -> Control | AN49: =IFERROR(IF(AK49="", "", _xlfn.XLOOKUP(AK49, CODES!A:A,CODES!I:I)), "") -> LNER | AO49: No driver allocated to class 5 move off Heaton.
A50: Root Cause | B50: 2611 | C50: 163696 | D50: 46053 | E50: 3S02 | F50: 05:23 NEVHILL D to DONCASTER | G50: XNL | H50: 5 | I50: 0 | J50: 5 | K50: 5 | L50: 0 | M50: 801225 | O50: 801225 | Q50: 9 | R50: 80x | S50: 43868 | T50: 3S02 5 LATE START XNL Unit late off depot, presented at 05:24:48. | U50: HRE Reject, MTIN – No. Depot report that the Driver was slow to depart. Class 3 only delay. | V50: TMV checked. JC 02/02 OTMR to check. Depot ops. JC 02/02 | W50: MHBM | X50: MHBM | Y50: MU | AA50: A | AB50: New | AC50: Accepted | AE50: 260131-163696 | AG50: Rejected - Class 3/5 | AH50: N | AI50: =IF(AD50="Availability", 0, IF(AND(AE50="Y", OR(J50>2, L50>0)), 1, 0)) -> 0 | AJ50: 701A | AK50: 1BD | AL50: =IFERROR(IF(AK50="", "", _xlfn.XLOOKUP(AK50, CODES!A:A,CODES!E:E)), "") -> Operational | AM50: =IFERROR(IF(AK50="", "", _xlfn.XLOOKUP(AK50, CODES!A:A,CODES!G:G)), "") -> Depot | AN50: =IFERROR(IF(AK50="", "", _xlfn.XLOOKUP(AK50, CODES!A:A,CODES!I:I)), "") -> Process | AO50: Unit late off depot.
A51: Root Cause | B51: 2611 | C51: 163621 | D51: 46053 | E51: 5S01 | F51: 04:25 DONCARIEP to DONCASTER | G51: DONCIEP | H51: 11 | I51: 0 | J51: 11 | K51: 11 | L51: 0 | M51: 800108 | O51: 800108 | Q51: 9 | R51: 80x | S51: 43578 | T51: 5S01 11 LATE START DONCIEP Unit late off depot - presented at 04:35:51. | U51: HRE Reject, MTIN – No. Depot report issues with the Form A. Class 5 only delay. | V51: TMV checked. JC 02/02 | W51: MHBH | X51: MHBH | Y51: MU | Z51: MU | AA51: A | AB51: Accepted | AC51: Accepted | AE51: 260131-163621 | AG51: Rejected - Class 3/5 | AH51: N | AI51: =IF(AD51="Availability", 0, IF(AND(AE51="Y", OR(J51>2, L51>0)), 1, 0)) -> 0 | AJ51: 701A | AK51: 1BD | AL51: =IFERROR(IF(AK51="", "", _xlfn.XLOOKUP(AK51, CODES!A:A,CODES!E:E)), "") -> Operational | AM51: =IFERROR(IF(AK51="", "", _xlfn.XLOOKUP(AK51, CODES!A:A,CODES!G:G)), "") -> Depot | AN51: =IFERROR(IF(AK51="", "", _xlfn.XLOOKUP(AK51, CODES!A:A,CODES!I:I)), "") -> Process | AO51: Unit late off depot.
A52: Root Cause | B52: 2611 | C52: 163330 | D52: 46052 | E52: 1N35 | F52: 23:08 London Kings Cross to York | G52: AAP PBR | J52: 9 | K52: 9 | L52: 0 | M52: NL08 | N52: 91119 | O52: NL08 | Q52: 11 | R52: 225 | T52: 1N35 BRAKES AAP PBR…..Brake application approaching Peterborough | U52: BCCB found tripped | V52: WO 5088836 | W52: MHBA | X52: MHBA | Y52: MN | AA52: A | AB52: Pending | AC52: Accepted | AE52: 260130-163330 | AH52: Y | AI52: =IF(AD52="Availability", 0, IF(AND(AE52="Y", OR(J52>2, L52>0)), 1, 0)) -> 0 | AJ52: 701D | AL52: =IFERROR(IF(AK52="", "", _xlfn.XLOOKUP(AK52, CODES!A:A,CODES!E:E)), "") | AM52: =IFERROR(IF(AK52="", "", _xlfn.XLOOKUP(AK52, CODES!A:A,CODES!G:G)), "") | AN52: =IFERROR(IF(AK52="", "", _xlfn.XLOOKUP(AK52, CODES!A:A,CODES!I:I)), "")
A53: Root Cause | B53: 2611 | C53: 163224 | D53: 46052 | E53: 5E01 | F53: 21:44 CRAIGNTNY to EDINBURGH | G53: XCN | H53: 24 | I53: 0 | J53: 24 | K53: 24 | L53: 0 | M53: 801207 | O53: 801207 | Q53: 9 | R53: 80x | S53: 43783 | T53: 5E01 24 LATE START XCN TAS REPORT FROM DRIVER STATES THE SET WASN'T READY AT THE DEPOT. Unit presented at 22:02:57. | U53: HRE Reject, MTIN – No. Depot report that the Driver was late to arrive. Class 5 only delay. | V53: TMV checked. JC 02/02 Drivers report requested - DR. JC 02/02 JP to do some digging. JC 03/02 No issues with planning. JP to email DR 10/02 S.B Depot process delay. | W53: MHBK | X53: MHBK | Y53: MU | AA53: A | AB53: New | AC53: Accepted | AE53: 260130-163224 | AG53: Rejected - Class 3/5 | AH53: N | AI53: =IF(AD53="Availability", 0, IF(AND(AE53="Y", OR(J53>2, L53>0)), 1, 0)) -> 0 | AJ53: 701A | AK53: 1BD | AL53: =IFERROR(IF(AK53="", "", _xlfn.XLOOKUP(AK53, CODES!A:A,CODES!E:E)), "") -> Operational | AM53: =IFERROR(IF(AK53="", "", _xlfn.XLOOKUP(AK53, CODES!A:A,CODES!G:G)), "") -> Depot | AN53: =IFERROR(IF(AK53="", "", _xlfn.XLOOKUP(AK53, CODES!A:A,CODES!I:I)), "") -> Process | AO53: Unit late off depot.
A54: Merged | B54: 2611 | C54: 162583 | D54: 46052 | F54: 16:27 NCASTLCEN to KINGS X | G54: DAR | H54: 5 | I54: 0 | J54: 5 | K54: 7 | L54: 0 | M54: 801104/11 | O54: 801111 | P54: 801104 | Q54: 5 | R54: 80x | S54: 43700 | T54: 1Y18 TRAIN DEFECT DAR Merge with TIN 162457. | U54: Please merge with TIN 162457 below as per 701D rules. | V54: Merge requested. JC 02/02 | W54: MHB2 | X54: MHB2 | Y54: M0 | AA54: D | AB54: New | AC54: Merged with Master | AE54: 260130-162583 | AG54: Merged | AH54: N | AI54: =IF(AD54="Availability", 0, IF(AND(AE54="Y", OR(J54>2, L54>0)), 1, 0)) -> 0 | AJ54: 701D | AK54: 2BM | AL54: =IFERROR(IF(AK54="", "", _xlfn.XLOOKUP(AK54, CODES!A:A,CODES!E:E)), "") -> LNER | AM54: =IFERROR(IF(AK54="", "", _xlfn.XLOOKUP(AK54, CODES!A:A,CODES!G:G)), "") -> Other | AN54: =IFERROR(IF(AK54="", "", _xlfn.XLOOKUP(AK54, CODES!A:A,CODES!I:I)), "") -> Merged - see Master | AO54: Merged with 162457.
A55: Root Cause | B55: 2611 | C55: 162457 | D55: 46052 | E55: 1Y18 | F55: 16:27 NCASTLCEN to KINGS X | G55: NCL | H55: 10 | I55: 0 | J55: 10 | K55: 54 | L55: 0 | M55: 801104/11 | O55: 801111 | P55: 801104 | Q55: 5 | R55: 80x | S55: 43700 | T55: 1Y18 UNIT FAULT TM Called to report issues with TMS very bad signal and hard to digest any info from the call, LNER later advise delays picked up at NCL when setting up for journey between 16:08 and 16:27 (call not received at the time) Further delays picked up at Darlington at approximately 16:56. LOG 260130-92 refers. SAP 8329911 refers - TMS 2304 reported at time of failure. | U55: MTIN YES, HRE ACCEPT - Root cause and coding TBC. | V55: Crew reports and coms requested. JC 02/02 Coms sent onto CPT. JC 03/02 5 minutes Newcastle, 5 minutes Darlington | W55: MHB2 | X55: MHB2 | Y55: M0 | AA55: A | AB55: New | AC55: Accepted | AE55: 260130-162457 | AG55: Accepted | AH55: Y | AI55: =IF(AD55="Availability", 0, IF(AND(AE55="Y", OR(J55>2, L55>0)), 1, 0)) -> 0 | AJ55: 701D | AK55: MEF | AL55: =IFERROR(IF(AK55="", "", _xlfn.XLOOKUP(AK55, CODES!A:A,CODES!E:E)), "") -> Monitoring System | AM55: =IFERROR(IF(AK55="", "", _xlfn.XLOOKUP(AK55, CODES!A:A,CODES!G:G)), "") -> TMS | AN55: =IFERROR(IF(AK55="", "", _xlfn.XLOOKUP(AK55, CODES!A:A,CODES!I:I)), "") -> Software | AO55: TMS issues reported prior to depature.
A56: Root Cause | B56: 2611 | C56: 162172 | D56: 46052 | E56: 1E13 | F56: 07:55 INVERNESS to KINGS X | G56: DON | H56: 0 | I56: 1.5 | J56: 0 | K56: 7 | L56: 1.5 | M56: 800107 | N56: 819107 | O56: 800107 | Q56: 9 | R56: 80x | S56: 43532 | T56: 1E13 UNIT FAULT DON Hitachi Maintenance Control have advised that 800107 - 1E13 has incurred a TMS Fault - 0316 "Main Transformer Fire Protection Fault" - on 819107. LOG 260130-75 refers. SAP 8329628 refers. | U56: HRE Reject, MTIN – No. LHD trainside plug found to have been ripped out of housing. Please see the report attached for further details. | V56: 1E13 part canx 1D23 full canx Further details requested from HRL of damaged component and strike pack info. JC 02/02 Update requested. JC 10/02 | W56: MHB1 | X56: MHB1 | Y56: MT | AA56: A | AB56: New | AC56: Discuss with HRL | AE56: 260130-162172 | AG56: Rejected | AH56: N | AI56: =IF(AD56="Availability", 0, IF(AND(AE56="Y", OR(J56>2, L56>0)), 1, 0)) -> 0 | AJ56: 701D | AK56: ZAI | AL56: =IFERROR(IF(AK56="", "", _xlfn.XLOOKUP(AK56, CODES!A:A,CODES!E:E)), "") -> Emergency Equipment | AM56: =IFERROR(IF(AK56="", "", _xlfn.XLOOKUP(AK56, CODES!A:A,CODES!G:G)), "") -> Fire System | AN56: =IFERROR(IF(AK56="", "", _xlfn.XLOOKUP(AK56, CODES!A:A,CODES!I:I)), "") -> LHD | AO56: LHD trainside plug found to have been ripped out of housing.
A57: Merged | B57: 2611 | C57: 161953 | D57: 46052 | F57: 08:30 EDINBURGH to KINGS X | G57: MPT HTONSJN | H57: 2 | I57: 0 | J57: 2 | K57: 9 | L57: 0 | M57: 801212 | N57: 825212 | O57: 801212 | Q57: 9 | R57: 80x | S57: 44064 | T57: 1E07 2 LOST MPT HTONSJN Brake hose (air leak) BCIC ISO. SAP 8328562 refers. **Merge with 161902** | U57: Please merge with TIN 161902 below as per 701D rules. | V57: Merge requested. JC 02/02 | W57: MHB2 | X57: MHB2 | Y57: MN | AA57: D | AB57: New | AC57: Merged with Master | AE57: 260130-161953 | AG57: Merged | AH57: N | AI57: =IF(AD57="Availability", 0, IF(AND(AE57="Y", OR(J57>2, L57>0)), 1, 0)) -> 0 | AJ57: 701D | AK57: 2BM | AL57: =IFERROR(IF(AK57="", "", _xlfn.XLOOKUP(AK57, CODES!A:A,CODES!E:E)), "") -> LNER | AM57: =IFERROR(IF(AK57="", "", _xlfn.XLOOKUP(AK57, CODES!A:A,CODES!G:G)), "") -> Other | AN57: =IFERROR(IF(AK57="", "", _xlfn.XLOOKUP(AK57, CODES!A:A,CODES!I:I)), "") -> Merged - see Master | AO57: Merged with 161902.
A58: Root Cause | B58: 2611 | C58: 161902 | D58: 46052 | E58: 1E07 | F58: 08:30 EDINBURGH to KINGS X | G58: GTHS MARSHALM | H58: 2 | I58: 0 | J58: 12 | K58: 26 | L58: 0 | M58: 801212 | N58: 825212 | O58: 801212 | Q58: 9 | R58: 80x | S58: 44064 | T58: 1E07 LOST GTHS MARSHALM Brake hose (air leak) BCIC ISO. SAP 8328562 refers. | U58: MTIN YES, HREACCEPT - Degraded running, BCU isolated on 825212. Air pipe above wheel 2 split and now replaced (not D&V). | W58: MHB2 | X58: MHB2 | Y58: MN | Z58: MN | AA58: A | AB58: Accepted | AC58: Accepted | AE58: 260130-161902 | AG58: Accepted | AH58: Y | AI58: =IF(AD58="Availability", 0, IF(AND(AE58="Y", OR(J58>2, L58>0)), 1, 0)) -> 0 | AJ58: 701D | AK58: BAC | AL58: =IFERROR(IF(AK58="", "", _xlfn.XLOOKUP(AK58, CODES!A:A,CODES!E:E)), "") -> Brake System | AM58: =IFERROR(IF(AK58="", "", _xlfn.XLOOKUP(AK58, CODES!A:A,CODES!G:G)), "") -> Bogie Brake Equipment | AN58: =IFERROR(IF(AK58="", "", _xlfn.XLOOKUP(AK58, CODES!A:A,CODES!I:I)), "") -> Brake Cylinder Hose | AO58: BCU isolated on 825212 due to split air pipe above wheel 2.
A59: Root Cause | B59: 2611 | C59: 161530 | D59: 46052 | E59: 1E13 | F59: 07:55 INVERNESS to KINGS X | G59: AVM | H59: 3 | I59: 0 | J59: 3 | K59: 3 | L59: 0 | M59: 800107 | O59: 800107 | Q59: 9 | R59: 80x | S59: 43532 | T59: 1E13 3 OVERTIME AVM TMS 0619 Door D Close Failure. Suspected debris in the door runner. SAP 8329440 refers. | U59: HRE Reject, MTIN – No. Debris found lodged in door runner preventing interlock from being achieved. | W59: MHBV | X59: MHBV | Y59: MF | Z59: MF | AA59: A | AB59: Accepted | AC59: Accepted | AE59: 260130-161530 | AG59: Rejected | AH59: N | AI59: =IF(AD59="Availability", 0, IF(AND(AE59="Y", OR(J59>2, L59>0)), 1, 0)) -> 0 | AJ59: 701A | AK59: 2BF | AL59: =IFERROR(IF(AK59="", "", _xlfn.XLOOKUP(AK59, CODES!A:A,CODES!E:E)), "") -> LNER | AM59: =IFERROR(IF(AK59="", "", _xlfn.XLOOKUP(AK59, CODES!A:A,CODES!G:G)), "") -> Other | AN59: =IFERROR(IF(AK59="", "", _xlfn.XLOOKUP(AK59, CODES!A:A,CODES!I:I)), "") -> Cleaning | AO59: Suspected debris in the door runner.
A60: Root Cause | B60: 2611 | C60: 161527 | D60: 46052 | E60: 1E13 | F60: 07:55 INVERNESS to KINGS X | G60: INV AVM | H60: 3 | I60: 0 | J60: 3 | K60: 3 | L60: 0 | M60: 800107 | N60: 815107 | O60: 800107 | Q60: 9 | R60: 80x | S60: 43532 | T60: 1E13 3 LOST INV AVM Degraded running, MTU aware and have suspected it may be related to drive belt. SAP 8321912 refers. | U60: MTIN YES, HRE ACCEPT - Degraded running, GU of 815107 LOOU (Drive Belt failure), MTU in attendance today 02/02. | W60: MHB1 | X60: MHB1 | Y60: MD | Z60: MD | AA60: A | AB60: Accepted | AC60: Accepted | AE60: 260130-161527 | AG60: Accepted | AH60: Y | AI60: =IF(AD60="Availability", 0, IF(AND(AE60="Y", OR(J60>2, L60>0)), 1, 0)) -> 0 | AJ60: 701D | AK60: DEG | AL60: =IFERROR(IF(AK60="", "", _xlfn.XLOOKUP(AK60, CODES!A:A,CODES!E:E)), "") -> Generator Units | AM60: =IFERROR(IF(AK60="", "", _xlfn.XLOOKUP(AK60, CODES!A:A,CODES!G:G)), "") -> Diesel Engine | AN60: =IFERROR(IF(AK60="", "", _xlfn.XLOOKUP(AK60, CODES!A:A,CODES!I:I)), "") -> Water Pump Belt | AO60: Degarded running, drive belt railure on 815107.
A61: Removed - Reassigned | B61: 2611 | C61: 161383 | D61: 46052 | E61: 1N03 | F61: 08:33 KINGS X to NCASTLCEN | G61: KGX | H61: 8 | I61: 0 | J61: 8 | K61: 16 | L61: 0 | M61: 801221 | N61: 823221 | O61: 801221 | Q61: 9 | R61: 80x | S61: 43859 | T61: 1N03 CANCELLED KGX Hitachi Maintenance Control Team Leader reminds that there is a dispensation on place that allows units with external door fault off a maintenance depot, contrarily to the latest DOTE update (the dispensation also involves defective pan cam). As a result, 801221, which has left Kings Cross towards Bounds Green will now return to Kings Cross, as it has been cleared that it can enter service. LOG 260130-66 refers. SAP 8328567 refers - *RES*TMS 1555 DOO Cam 4 Network Error. | U61: HRE Reject, MTIN – No. TMS 1555 DOO Cam 4 Network Error reported by the DVR on route from BGN to KGX. 1N03 initially cancelled by LNER as per the DOTE in error, then reinstated after MC advised of a dispensation allowing the Unit to remain in service. LNER Log 260130-66 refers. | V61: Possible referral to control - voice coms to request. Unit came off on 5S07 (07:10). JC 03/02 Referral to ops requested. JC 03/02 | W61: THBN | X61: THBN | Y61: TB | Z61: TB | AA61: A | AB61: Accepted | AC61: Referred | AE61: 260130-161383 | AG61: Rejected | AH61: N | AI61: =IF(AD61="Availability", 0, IF(AND(AE61="Y", OR(J61>2, L61>0)), 1, 0)) -> 0 | AJ61: 701B | AK61: 1CA | AL61: =IFERROR(IF(AK61="", "", _xlfn.XLOOKUP(AK61, CODES!A:A,CODES!E:E)), "") -> Operational | AM61: =IFERROR(IF(AK61="", "", _xlfn.XLOOKUP(AK61, CODES!A:A,CODES!G:G)), "") -> Control | AN61: =IFERROR(IF(AK61="", "", _xlfn.XLOOKUP(AK61, CODES!A:A,CODES!I:I)), "") -> LNER | AO61: Service cancelled owing to CCTV fault. Dispensation in place to allow unit into service.
A62: Root Cause | B62: 2611 | C62: 161321 | D62: 46052 | E62: 1E05 | F62: 07:30 EDINBURGH to KINGS X | G62: EDB MNKTNHALJ | H62: 6 | I62: 0 | J62: 6 | K62: 9 | L62: 0 | M62: 800105 | N62: 811105 | O62: 800105 | Q62: 9 | R62: 80x | S62: 43572 | T62: 1E05 TMS FLT MUB TMS 6602 No Current Draw from OHL. SAP 8329330 refers. | U62: HRE Reject, MTIN – No. Driver did not follow guidance displayed on the TMS bringing the train to a stand unnecessarily. Please see the report attached for further details. | V62: OTMR to check. JC 02/02 Fruther details requested from HRL. JC 02/02 Unit was traversing a neutral section at time of alert, suspected noise induced failure. JC 02/02 JH to discuss with PL. To be accepted as M9 NFF. JC 02/02 Disputed with HRL. JC 13/02 | W62: MHB1 | X62: MHB1 | Y62: M0 | AA62: A | AB62: New | AC62: Refer to Level 2 | AE62: 260130-161321 | AG62: Rejected | AH62: N | AI62: =IF(AD62="Availability", 0, IF(AND(AE62="Y", OR(J62>2, L62>0)), 1, 0)) -> 0 | AJ62: 701D | AK62: 1AA | AL62: =IFERROR(IF(AK62="", "", _xlfn.XLOOKUP(AK62, CODES!A:A,CODES!E:E)), "") -> Operational | AM62: =IFERROR(IF(AK62="", "", _xlfn.XLOOKUP(AK62, CODES!A:A,CODES!G:G)), "") -> Staff | AN62: =IFERROR(IF(AK62="", "", _xlfn.XLOOKUP(AK62, CODES!A:A,CODES!I:I)), "") -> Driver | AO62: Driver did not follow on screen guidance on the TMS.
A63: Removed - Reassigned | B63: 2611 | C63: 160949 | D63: 46052 | E63: 3Y03 | F63: 04:35 DONCARIEP to YORK | G63: DONCIEP | H63: 4 | I63: 0 | J63: 4 | K63: 4 | L63: 0 | M63: 800/801 | O63: 800205 | Q63: 5 | R63: 80x | S63: 43714 | T63: 3Y03 DEPOT OPS DONCIEP Unit late off depot, presented at 04:37:02. | U63: HRE Reject, MTIN – No. Depot report Driver did not call to advise that they were ready to depart until 04:36 (booked departure 04:35). Class 3 only delay. | V63: TMC checked. JC 02/02 | W63: THB2 | X63: THB2 | Y63: TG | Z63: TG | AA63: A | AB63: Accepted | AC63: Referred | AE63: 260130-160949 | AG63: Rejected - Class 3/5 | AH63: N | AI63: =IF(AD63="Availability", 0, IF(AND(AE63="Y", OR(J63>2, L63>0)), 1, 0)) -> 0 | AJ63: 701C | AK63: 1AA | AL63: =IFERROR(IF(AK63="", "", _xlfn.XLOOKUP(AK63, CODES!A:A,CODES!E:E)), "") -> Operational | AM63: =IFERROR(IF(AK63="", "", _xlfn.XLOOKUP(AK63, CODES!A:A,CODES!G:G)), "") -> Staff | AN63: =IFERROR(IF(AK63="", "", _xlfn.XLOOKUP(AK63, CODES!A:A,CODES!I:I)), "") -> Driver | AO63: Unit late off depot.
A64: Root Cause | B64: 2611 | C64: 160943 | D64: 46052 | E64: 5S01 | F64: 04:23 DONCARIEP to DONCASTER | G64: DONCIEP | H64: 11 | I64: 0 | J64: 11 | K64: 11 | L64: 0 | M64: 800112 | O64: 800112 | Q64: 9 | R64: 80x | S64: 43536 | T64: 5S01 DEPOT OPS DONCIEP Unit late off depot, presented at 04:32:09. | U64: MTIN YES, HRE ACCEPT - Traction software related issue. | V64: TMC checked. JC 02/02 Recode to 701D requested. JC 12/02 | W64: MHBH | X64: MHBH | Y64: MU | AA64: A | AB64: New | AC64: Accepted | AE64: 260130-160943 | AG64: Accepted | AH64: Y | AI64: =IF(AD64="Availability", 0, IF(AND(AE64="Y", OR(J64>2, L64>0)), 1, 0)) -> 0 | AJ64: 701A | AK64: PHAA | AL64: =IFERROR(IF(AK64="", "", _xlfn.XLOOKUP(AK64, CODES!A:A,CODES!E:E)), "") -> Traction and Power Equipment | AM64: =IFERROR(IF(AK64="", "", _xlfn.XLOOKUP(AK64, CODES!A:A,CODES!G:G)), "") -> Traction Converter | AN64: =IFERROR(IF(AK64="", "", _xlfn.XLOOKUP(AK64, CODES!A:A,CODES!I:I)), "") -> Software | AO64: Unit late off depot due to traction software related issue.
A65: Removed - Reassigned | B65: 2611 | C65: 160060 | D65: 46051 | E65: 1D23 | F65: 16:39 KINGS X to HARROGATE | G65: GRA NNG | H65: 39 | I65: 1 | J65: 39 | K65: 227 | L65: 1 | M65: 800101 | N65: 811101 | O65: 800101 | Q65: 9 | R65: 80x | S65: 43920 | T65: 1D23 BRAKE/WHLS GRA NNG NR TRC Central advises 1D23 is at a stand on approach to Newark Northgate station following activation of Balderton HABD. Reported temps were 201 degrees on axle number 3 and 160 degrees on axle number 15. LOG 260129-112 refers. SAP 8328468 refers - Wheel 3 HABD Detection | U65: MTIN NO, HRE REJECT - Unit inspected with NFF, Unit passed the next lineside HABD with no activation. | V65: Details passed onto JP. JC 02/02 Details requested from HRL. JC 02/02 | W65: NRIN | X65: IQIJ | Y65: IN | AA65: A | AB65: New | AC65: Referred | AE65: 260129-160060 | AG65: Rejected | AH65: N | AI65: =IF(AD65="Availability", 0, IF(AND(AE65="Y", OR(J65>2, L65>0)), 1, 0)) -> 0 | AJ65: 302B | AK65: 1DC | AL65: =IFERROR(IF(AK65="", "", _xlfn.XLOOKUP(AK65, CODES!A:A,CODES!E:E)), "") -> Operational | AM65: =IFERROR(IF(AK65="", "", _xlfn.XLOOKUP(AK65, CODES!A:A,CODES!G:G)), "") -> NR | AN65: =IFERROR(IF(AK65="", "", _xlfn.XLOOKUP(AK65, CODES!A:A,CODES!I:I)), "") -> Safety Equipment | AO65: Lineside HABD activation reported by NR. Unit inpsected with NFF.
A66: Root Cause | B66: 2611 | C66: 159731 | D66: 46051 | E66: 1B89 | F66: 15:20 LINCLNCEN to KINGS X | G66: GRA | H66: 13 | I66: 0 | J66: 13 | K66: 16 | L66: 0 | M66: 800205 | N66: 812205 | O66: 800205 | Q66: 5 | R66: 80x | S66: 43714 | T66: 1B89 UNIT FLT GRA Driver contacted maintenance control at Grantham. Tried to press electric nothing happened asked driver to lower the PAN but driver said pan didn't drop. HMAX only shows PAN UP operation. driver was instructed to start GU's by change over process this lowered the pan. once pan was reraised ole was live and all fault cleared with APS as normal. LOG 260129-109 refers. SAP 8328262 refers - TMS 4052 Transformer Oil Flow Failure | U66: MTIN YES, HRE ACCEPT - Root cause TBC. | W66: MHB1 | X66: MHB1 | Y66: M1 | AA66: A | AB66: New | AC66: Accepted | AE66: 260129-159731 | AG66: Accepted | AH66: Y | AI66: =IF(AD66="Availability", 0, IF(AND(AE66="Y", OR(J66>2, L66>0)), 1, 0)) -> 0 | AJ66: 701D | AK66: PB9 | AL66: =IFERROR(IF(AK66="", "", _xlfn.XLOOKUP(AK66, CODES!A:A,CODES!E:E)), "") -> Traction and Power Equipment | AM66: =IFERROR(IF(AK66="", "", _xlfn.XLOOKUP(AK66, CODES!A:A,CODES!G:G)), "") -> APS | AN66: =IFERROR(IF(AK66="", "", _xlfn.XLOOKUP(AK66, CODES!A:A,CODES!I:I)), "") -> No Fault Identified | AO66: TMS 4052 Transformer Oil Flow Failure recorded on HFMT, root cause TBC.
A67: Root Cause | B67: 2611 | C67: 158923 | D67: 46051 | E67: 1D08 | G67: KGX | J67: 4 | K67: 18 | L67: 0 | M67: NL15 | O67: NL15 | Q67: 11 | R67: 225 | T67: 1D08 4 LATE START KGX | W67: MHBA | X67: MHBA | Y67: MB | AA67: A | AB67: New | AC67: Investigation | AE67: 260129-158923 | AI67: =IF(AD67="Availability", 0, IF(AND(AE67="Y", OR(J67>2, L67>0)), 1, 0)) -> 0 | AJ67: 701D | AL67: =IFERROR(IF(AK67="", "", _xlfn.XLOOKUP(AK67, CODES!A:A,CODES!E:E)), "") | AM67: =IFERROR(IF(AK67="", "", _xlfn.XLOOKUP(AK67, CODES!A:A,CODES!G:G)), "") | AN67: =IFERROR(IF(AK67="", "", _xlfn.XLOOKUP(AK67, CODES!A:A,CODES!I:I)), "")
A68: Removed - Reassigned | B68: 2611 | C68: 157843 | D68: 46050 | E68: 1D32 | F68: 21:08 KINGS X to LEEDS | G68: XHO PBO | H68: 3 | I68: 0 | J68: 3 | K68: 3 | L68: 0 | M68: 801104 | O68: 801104 | P68: 801101 | Q68: 5 | R68: 80x | S68: 43672 | T68: 1D32 3 LOST XHO PBO POWER CHANGE OVER FAULT X2 HAD TO PAN UP AT BELOW 20MPH SO DELAY CAUSED. Driver report required. | U68: MTIN NO, HRE REJECT - As per the Driver’s report, station delay due to a passenger issue on the Platform, not a train fault. | V68: Driver report requested - JM. JC 29/01 Chaser email sent. JC 03/02 TM report required, delay caused by passenger on platform. JC 03/02 | W68: THB2 | X68: THB2 | Y68: TW | Z68: TW | AA68: A | AB68: Accepted | AC68: Referred | AE68: 260128-157843 | AG68: Rejected | AH68: N | AI68: =IF(AD68="Availability", 0, IF(AND(AE68="Y", OR(J68>2, L68>0)), 1, 0)) -> 0 | AJ68: 701C | AK68: 1AA | AL68: =IFERROR(IF(AK68="", "", _xlfn.XLOOKUP(AK68, CODES!A:A,CODES!E:E)), "") -> Operational | AM68: =IFERROR(IF(AK68="", "", _xlfn.XLOOKUP(AK68, CODES!A:A,CODES!G:G)), "") -> Staff | AN68: =IFERROR(IF(AK68="", "", _xlfn.XLOOKUP(AK68, CODES!A:A,CODES!I:I)), "") -> Driver | AO68: Delay due to passenger on station.
A69: Removed - Reassigned | B69: 2611 | C69: 157818 | D69: 46050 | E69: 1E32 | F69: 21:19 CRAIGNTNY to EDINBURGH | G69: XCN | H69: 6 | I69: 0 | J69: 6 | K69: 10 | L69: 0 | M69: 801218 | O69: 801218 | Q69: 9 | R69: 80x | S69: 43998 | T69: 1E32 4 LATE START EDB 5E32 6 LATE START XCN Unit presented late from depot, TMV checked and not awaiting signals. | U69: HRE Reject, MTIN – no. Depot report Unit held waiting signals. Class 5 only delay. | W69: THBN | X69: THBN | Y69: TB | Z69: TB | AA69: A | AB69: Accepted | AC69: Referred | AE69: 260128-157818 | AG69: Rejected - Class 3/5 | AH69: N | AI69: =IF(AD69="Availability", 0, IF(AND(AE69="Y", OR(J69>2, L69>0)), 1, 0)) -> 0 | AJ69: 701B | AK69: 1BD | AL69: =IFERROR(IF(AK69="", "", _xlfn.XLOOKUP(AK69, CODES!A:A,CODES!E:E)), "") -> Operational | AM69: =IFERROR(IF(AK69="", "", _xlfn.XLOOKUP(AK69, CODES!A:A,CODES!G:G)), "") -> Depot | AN69: =IFERROR(IF(AK69="", "", _xlfn.XLOOKUP(AK69, CODES!A:A,CODES!I:I)), "") -> Process | AO69: Unit late off depot.
A70: Root Cause | B70: 2611 | C70: 156801 | D70: 46050 | E70: 1S09 | F70: 09:03 KINGS X to EDINBURGH | G70: MPT ALM | H70: 6 | I70: 0 | J70: 6 | K70: 6 | L70: 0 | M70: 801215 | N70: 826215 | O70: 801215 | Q70: 9 | R70: 80x | S70: 43843 | T70: 1S09 2 LOST MPT ALM BCU fault reported at NCL - 10 mph below line speed. Will be above 2 minute delay. SAP 8325594 refers. RES 92742 refers. | U70: MTIN YES, HRE ACCEPT - Air leak found from a split hose on car 6, wheel 1 calliper. Hose replaced, coding TBC. | V70: Details passed onto CPT. JC 30/01 | W70: MHB2 | X70: MHB2 | Y70: MN | AA70: A | AB70: New | AC70: Accepted | AE70: 260128-156801 | AG70: Accepted | AH70: Y | AI70: =IF(AD70="Availability", 0, IF(AND(AE70="Y", OR(J70>2, L70>0)), 1, 0)) -> 0 | AJ70: 701D | AK70: BBJ | AL70: =IFERROR(IF(AK70="", "", _xlfn.XLOOKUP(AK70, CODES!A:A,CODES!E:E)), "") -> Brake System | AM70: =IFERROR(IF(AK70="", "", _xlfn.XLOOKUP(AK70, CODES!A:A,CODES!G:G)), "") -> Brake Control Unit | AN70: =IFERROR(IF(AK70="", "", _xlfn.XLOOKUP(AK70, CODES!A:A,CODES!I:I)), "") -> Pipework | AO70: Time lost in running due to isolated BCU. Air leak found from a split hose on car 6, wheel 1 calliper.
A71: Root Cause | B71: 2611 | C71: 156719 | D71: 46050 | E71: 1S12 | F71: 10:30 KINGS X to EDINBURGH | G71: YRK | H71: 39 | I71: 1 | J71: 39 | K71: 69 | L71: 1 | M71: 801214 | N71: 821214 | O71: 801214 | Q71: 9 | R71: 80x | S71: 43943 | T71: 1S12 10 OVERTIME YRK No APS on Car 1 only. ACTa board replaced. LOG 260128-126 refers. SAP 8326649 refers. | U71: MTIN NO, HRE REJECT - ACTa board was found hanging loose with all 4 mountings smashed. Signs of impact damage found on the external side of the mounting panel. Please see the report attached for further details. | V71: To be accepted. JC 02/02 | W71: MHB2 | X71: MHB2 | Y71: MD | Z71: MD | AA71: A | AB71: Accepted | AC71: Accepted | AE71: 260128-156719 | AG71: Rejected | AH71: N | AI71: =IF(AD71="Availability", 0, IF(AND(AE71="Y", OR(J71>2, L71>0)), 1, 0)) -> 0 | AJ71: 701D | AK71: PBAB | AL71: =IFERROR(IF(AK71="", "", _xlfn.XLOOKUP(AK71, CODES!A:A,CODES!E:E)), "") -> Traction and Power Equipment | AM71: =IFERROR(IF(AK71="", "", _xlfn.XLOOKUP(AK71, CODES!A:A,CODES!G:G)), "") -> APS | AN71: =IFERROR(IF(AK71="", "", _xlfn.XLOOKUP(AK71, CODES!A:A,CODES!I:I)), "") -> ACTa Mounts | AO71: Issues obtaining APS on unit. ACTa board was found hanging loose with all 4 mountings smashed.
A72: Root Cause | B72: 2611 | C72: 156693 | D72: 46050 | E72: 1Y83 | F72: 12:27 YORK to KINGS X | G72: YRK | H72: 0 | I72: 1 | J72: 0 | K72: 7 | L72: 1 | M72: 801102 | N72: 825102 | O72: 801102 | Q72: 5 | R72: 80x | S72: 43728 | T72: 1Y83 CANCELLED YRK ETCS DMI Screen Blank or Distorted LOG 260128-125 refers. SAP 8326665 refers. | U72: MTIN YES, HRE ACCEPT - ETCS DMI Screen replaced. | W72: MHB2 | X72: MHB2 | Y72: M2 | Z72: M2 | AA72: A | AB72: Accepted | AC72: Accepted | AE72: 260128-156693 | AG72: Accepted | AH72: Y | AI72: =IF(AD72="Availability", 0, IF(AND(AE72="Y", OR(J72>2, L72>0)), 1, 0)) -> 0 | AJ72: 701D | AK72: SEH | AL72: =IFERROR(IF(AK72="", "", _xlfn.XLOOKUP(AK72, CODES!A:A,CODES!E:E)), "") -> Safety System | AM72: =IFERROR(IF(AK72="", "", _xlfn.XLOOKUP(AK72, CODES!A:A,CODES!G:G)), "") -> ETCS | AN72: =IFERROR(IF(AK72="", "", _xlfn.XLOOKUP(AK72, CODES!A:A,CODES!I:I)), "") -> ETCS DMI | AO72: ETCS DMI Screen Blank reported by driver. Screen renewed.
A73: Root Cause | B73: 2611 | C73: 156663 | D73: 46050 | E73: 1A19 | F73: 11:37 Bradford Forster Square - London Kings Cross | G73: LDS | J73: 22 | K73: 435 | L73: 5 | M73: NL26 | N73: 12465 | O73: NL26 | Q73: 11 | R73: 225 | T73: 1A19 UNIT ISSUE COPHWJN…..Loss of main res | U73: M/R hose parted from star valve | V73: WO 5088783 | W73: MHBA | X73: MHBA | Y73: MB | Z73: MB | AA73: A | AB73: Accepted | AC73: Accepted | AE73: 260128-156663 | AH73: Y | AI73: =IF(AD73="Availability", 0, IF(AND(AE73="Y", OR(J73>2, L73>0)), 1, 0)) -> 0 | AJ73: 701D | AK73: 225-APF | AL73: =IFERROR(IF(AK73="", "", _xlfn.XLOOKUP(AK73, CODES!A:A,CODES!E:E)), "") -> Air System | AM73: =IFERROR(IF(AK73="", "", _xlfn.XLOOKUP(AK73, CODES!A:A,CODES!G:G)), "") -> Pipe work | AN73: =IFERROR(IF(AK73="", "", _xlfn.XLOOKUP(AK73, CODES!A:A,CODES!I:I)), "") -> Main reservoir coupling hose cock
A74: Removed | B74: 2611 | C74: 155833 | D74: 46050 | F74: 06:25 BOUNDGNCS to KINGS X | G74: BNDSGRN | H74: 22 | I74: 0 | J74: 22 | K74: 24 | L74: 0 | M74: 801225 | O74: 801225 | Q74: 9 | R74: 80x | S74: 43868 | T74: 5S06 DEPOT OPS BNDSGRN TMV SHOWS 5S06 LATE START FROM BOUNDGNCS. | U74: HRE Reject, MTIN – No. Depot report 5S06 delayed following late departing 5D03, 5S05 & 3H01, all held & delayed due to Freight service 4L88 running 126L passing on the mainline. Class 5 only delay. | V74: DRV reports, Late departure awaiting right away from BN, further delays due to congestion & backlog. Email sent to JP. 29/01 s.b Awaiting dispute comments, NR have taken it. JC 03/02 | W74: MHBJ | X74: MHBJ | Y74: MU | AA74: D | AB74: New | AC74: Referred | AE74: 260128-155833 | AG74: Rejected - Class 3/5 | AH74: N | AI74: =IF(AD74="Availability", 0, IF(AND(AE74="Y", OR(J74>2, L74>0)), 1, 0)) -> 0 | AJ74: 701A | AK74: 1DB | AL74: =IFERROR(IF(AK74="", "", _xlfn.XLOOKUP(AK74, CODES!A:A,CODES!E:E)), "") -> Operational | AM74: =IFERROR(IF(AK74="", "", _xlfn.XLOOKUP(AK74, CODES!A:A,CODES!G:G)), "") -> NR | AN74: =IFERROR(IF(AK74="", "", _xlfn.XLOOKUP(AK74, CODES!A:A,CODES!I:I)), "") -> Regulation | AO74: Unit late from depot.
A75: Root Cause | B75: 2611 | C75: 155682 | D75: 46050 | E75: 5A05 | F75: 05:35 Neville Hill T&R.S.M.D - Leeds | G75: XNL | J75: 8 | K75: 8 | L75: 0 | M75: NL17 | O75: NL17 | Q75: 11 | R75: 225 | T75: 5A05 8 LATE START XNL | U75: CONGESTION AT WEST END DUE TO TELEPHONE LINE DOWN | W75: MHBM | X75: MHBM | Y75: MU | AA75: A | AB75: New | AC75: Accepted | AE75: 260128-155682 | AH75: N | AI75: =IF(AD75="Availability", 0, IF(AND(AE75="Y", OR(J75>2, L75>0)), 1, 0)) -> 0 | AJ75: 701A | AL75: =IFERROR(IF(AK75="", "", _xlfn.XLOOKUP(AK75, CODES!A:A,CODES!E:E)), "") | AM75: =IFERROR(IF(AK75="", "", _xlfn.XLOOKUP(AK75, CODES!A:A,CODES!G:G)), "") | AN75: =IFERROR(IF(AK75="", "", _xlfn.XLOOKUP(AK75, CODES!A:A,CODES!I:I)), "")
A76: Root Cause | B76: 2611 | C76: 155663 | D76: 46050 | E76: 3A10 | F76: 05:25 Neville Hill T&R.S.M.D - Skipton | G76: 3A10 | J76: 7 | K76: 7 | L76: 0 | M76: NL08 | O76: NL08 | Q76: 11 | R76: 225 | T76: 3A10 7 LATE START XNL | U76: CONGESTION AT WEST END DUE TO TELEPHONE LINE DOWN | W76: MHBM | X76: MHBM | Y76: MU | AA76: A | AB76: New | AC76: Accepted | AE76: 260128-155663 | AH76: N | AI76: =IF(AD76="Availability", 0, IF(AND(AE76="Y", OR(J76>2, L76>0)), 1, 0)) -> 0 | AJ76: 701A | AL76: =IFERROR(IF(AK76="", "", _xlfn.XLOOKUP(AK76, CODES!A:A,CODES!E:E)), "") | AM76: =IFERROR(IF(AK76="", "", _xlfn.XLOOKUP(AK76, CODES!A:A,CODES!G:G)), "") | AN76: =IFERROR(IF(AK76="", "", _xlfn.XLOOKUP(AK76, CODES!A:A,CODES!I:I)), "")
A77: Root Cause | B77: 2611 | C77: 155653 | D77: 46050 | E77: 3A08 | F77: 05:12 NEVHILL D to HARROGATE | G77: XNL | H77: 5 | I77: 0 | J77: 5 | K77: 5 | L77: 0 | M77: 800102 | O77: 800102 | Q77: 9 | R77: 80x | S77: 43545 | T77: 3A08 5 LATE START XNL INTERPOSED AT 0515. CONGESTION AT THE WESTEND OF THE DEPOT. WESTEND CONSOLE LANDLINE HAS GONE DOWN. DRIVERS STRUGGLING TO GET A HOLD OF WESTEND FOR DEPARTURE. | U77: HRE Reject, MTIN – No. Depot report congestion at the West End due to the telephone lines being down causing communication issues. Class 3 only delay. | W77: MHBM | X77: MHBM | Y77: MU | Z77: MU | AA77: A | AB77: Accepted | AC77: Accepted | AE77: 260128-155653 | AG77: Rejected - Class 3/5 | AH77: N | AI77: =IF(AD77="Availability", 0, IF(AND(AE77="Y", OR(J77>2, L77>0)), 1, 0)) -> 0 | AJ77: 701A | AK77: 1BA | AL77: =IFERROR(IF(AK77="", "", _xlfn.XLOOKUP(AK77, CODES!A:A,CODES!E:E)), "") -> Operational | AM77: =IFERROR(IF(AK77="", "", _xlfn.XLOOKUP(AK77, CODES!A:A,CODES!G:G)), "") -> Depot | AN77: =IFERROR(IF(AK77="", "", _xlfn.XLOOKUP(AK77, CODES!A:A,CODES!I:I)), "") -> InfraStructure | AO77: Unit late off depot, west end console landline down.
A78: Root Cause | B78: 2611 | C78: 155636 | D78: 46050 | E78: 3S02 | F78: 05:00 NEVHILL D to DONCASTER | G78: XNL | H78: 7 | I78: 0 | J78: 7 | K78: 7 | L78: 0 | M78: 801228 | O78: 801228 | Q78: 9 | R78: 80x | S78: 43964 | T78: 3S02 7 LATE START XNL INTERPOSED AT 0506. CONGESTION AT THE WEST END OF THE DEPOT. WESTEND CONSOLE LANDLINE HAS GONE DOWN. DRIVERS STRUGGLING TO GET A HOLD OF WESTEND FOR DEPARTURE. | U78: HRE Reject, MTIN – No. Depot report congestion at the West End due to the telephone lines being down causing communication issues. Class 3 only delay. | W78: MHBM | X78: MHBM | Y78: MU | Z78: MU | AA78: A | AB78: Accepted | AC78: Accepted | AE78: 260128-155636 | AG78: Rejected - Class 3/5 | AH78: N | AI78: =IF(AD78="Availability", 0, IF(AND(AE78="Y", OR(J78>2, L78>0)), 1, 0)) -> 0 | AJ78: 701A | AK78: 1BA | AL78: =IFERROR(IF(AK78="", "", _xlfn.XLOOKUP(AK78, CODES!A:A,CODES!E:E)), "") -> Operational | AM78: =IFERROR(IF(AK78="", "", _xlfn.XLOOKUP(AK78, CODES!A:A,CODES!G:G)), "") -> Depot | AN78: =IFERROR(IF(AK78="", "", _xlfn.XLOOKUP(AK78, CODES!A:A,CODES!I:I)), "") -> InfraStructure | AO78: Unit late off depot, west end console landline down.
A79: Removed | B79: 2611 | C79: 156 | D79: 46050 | F79: 10:30 KINGS X to EDINBURGH | G79: YRK | H79: 43 | I79: 1 | J79: 39 | K79: 69 | L79: 1 | M79: 801214 | N79: 821214 | O79: 801214 | Q79: 9 | R79: 80x | S79: 43943 | T79: 1S12 10 OVERTIME YRK No APS on Car 1 only. ACTa board replaced. LOG 260128-126 refers. SAP 8326649 refers. | U79: Under investigation. | V79: 156719 refers - incident to be removed. | W79: MHB2 | X79: MHB2 | Y79: M1 | AA79: D | AB79: New | AC79: Referred | AE79: 260128-000156 | AG79: Rejected | AH79: N | AI79: =IF(AD79="Availability", 0, IF(AND(AE79="Y", OR(J79>2, L79>0)), 1, 0)) -> 0 | AJ79: 701D | AL79: =IFERROR(IF(AK79="", "", _xlfn.XLOOKUP(AK79, CODES!A:A,CODES!E:E)), "") | AM79: =IFERROR(IF(AK79="", "", _xlfn.XLOOKUP(AK79, CODES!A:A,CODES!G:G)), "") | AN79: =IFERROR(IF(AK79="", "", _xlfn.XLOOKUP(AK79, CODES!A:A,CODES!I:I)), "")
A80: Removed | B80: 2611 | C80: 154783 | D80: 46049 | F80: 15:03 KINGS X to EDINBURGH | G80: NCL | H80: 5 | I80: 0 | J80: 5 | K80: 5 | L80: 0 | M80: 801223 | N80: 821223 | O80: 801223 | Q80: 9 | R80: 80x | S80: 43896 | T80: 1S21 5 OVERTIME NCL ONCE 1S21 WAS MET IN, FITTERS ATTENDED AS NETWORK RAIL HAD REQUESTED THE FORWARD FACING CCTV FOOTAGE TO ESTABLISH THE ROUTE CAUSE OF THE DELAY AT THIRK REGARDING Y413 SIGNAL CAUSING AN EMERGENCT BRAKE APPLICATION. LOG 260127-62 refers. SAP 8325543 refers. | U80: HRE Reject, MTIN – No. Station overtime at Newcastle whilst a TRI attended to download FF CCTV after an alleged Driver overspeed event subsequently confirmed as a signal reversion at Y429 near Thirsk. LNER Log 260127-62 refers. | V80: Details sent onto JP. JC 28/01 | W80: MHBR | X80: MHBR | Y80: MF | AA80: D | AB80: New | AC80: Referred | AE80: 260127-154783 | AG80: Rejected | AH80: N | AI80: =IF(AD80="Availability", 0, IF(AND(AE80="Y", OR(J80>2, L80>0)), 1, 0)) -> 0 | AJ80: 701A | AK80: 1DC | AL80: =IFERROR(IF(AK80="", "", _xlfn.XLOOKUP(AK80, CODES!A:A,CODES!E:E)), "") -> Operational | AM80: =IFERROR(IF(AK80="", "", _xlfn.XLOOKUP(AK80, CODES!A:A,CODES!G:G)), "") -> NR | AN80: =IFERROR(IF(AK80="", "", _xlfn.XLOOKUP(AK80, CODES!A:A,CODES!I:I)), "") -> Safety Equipment | AO80: Station overtime at Newcastle whilst a TRI attended to download FF CCTV after an alleged Driver overspeed event subsequently confirmed as a signal reversion at Y429 near Thirsk
A81: Merged | B81: 2611 | C81: 154667 | D81: 46049 | F81: 18:30 KINGS X to EDINBURGH | G81: KINGS X | H81: 0 | I81: 1 | J81: 0 | K81: 0 | L81: 1 | M81: 801214 | N81: 821214 | O81: 801214 | Q81: 9 | R81: 80x | S81: 43943 | T81: 1S28 CANCELLED KGX ETCS DMI Screen Blank or Distorted. 1E18 & 1S28 both cancelled. *Merge with 153483* LOG 260127-41 refers. SAP 8325270 refers. | U81: Reactionary cancellation to 1S09 TIN 153483, recorded as merged by HRE. | V81: Merge request sent to JP. JC 28/01 | W81: MHB2 | X81: MHB2 | Y81: M0 | AA81: A | AB81: New | AC81: Merged with Master | AE81: 260127-154667 | AG81: Merged | AH81: N | AI81: =IF(AD81="Availability", 0, IF(AND(AE81="Y", OR(J81>2, L81>0)), 1, 0)) -> 0 | AJ81: 701D | AK81: 2BM | AL81: =IFERROR(IF(AK81="", "", _xlfn.XLOOKUP(AK81, CODES!A:A,CODES!E:E)), "") -> LNER | AM81: =IFERROR(IF(AK81="", "", _xlfn.XLOOKUP(AK81, CODES!A:A,CODES!G:G)), "") -> Other | AN81: =IFERROR(IF(AK81="", "", _xlfn.XLOOKUP(AK81, CODES!A:A,CODES!I:I)), "") -> Merged - see Master | AO81: Merged with 153483.
A82: Merged | B82: 2611 | C82: 154662 | D82: 46049 | F82: 18:09 KINGS X to HULL | G82: KGX | H82: 0 | I82: 1 | J82: 0 | K82: 7 | L82: 1 | M82: 800204 | N82: 815204 | O82: 800204 | Q82: 5 | R82: 80x | S82: 43714 | T82: 1H20 CANCELLED KGX 1H20 1809 Kings Cross to Hull would be cancelled due to fault on 800204 *Merge with 153582* LOG 260127-46 refers. SAP 8325301 refers. | U82: Reactionary cancellation to 1A15 TIN 153582, recorded as merged by HRE. | V82: Merge request sent to JP. JC 28/01 | W82: MHB1 | X82: MHB1 | Y82: M0 | AA82: A | AB82: New | AC82: Merged with Master | AE82: 260127-154662 | AG82: Merged | AH82: N | AI82: =IF(AD82="Availability", 0, IF(AND(AE82="Y", OR(J82>2, L82>0)), 1, 0)) -> 0 | AJ82: 701D | AK82: 2BM | AL82: =IFERROR(IF(AK82="", "", _xlfn.XLOOKUP(AK82, CODES!A:A,CODES!E:E)), "") -> LNER | AM82: =IFERROR(IF(AK82="", "", _xlfn.XLOOKUP(AK82, CODES!A:A,CODES!G:G)), "") -> Other | AN82: =IFERROR(IF(AK82="", "", _xlfn.XLOOKUP(AK82, CODES!A:A,CODES!I:I)), "") -> Merged - see Master | AO82: Merged with 153582.
A83: Merged | B83: 2611 | C83: 154459 | D83: 46049 | F83: 12:47 KINGS X to LINCLNCEN | G83: N/A | H83: 0 | I83: 0.5 | J83: 0 | K83: 0 | L83: 1 | M83: 801104 | O83: 801104 | Q83: 5 | R83: 80x | S83: 43672 | T83: 1B86 CANCELLED NNG LCN 5 car electric set 801104 which was spare at Bounds Green would be utilised vice 800204. 1B86 would terminate at Newark Northgate and 1B89 would start at Newark Northgate as a consequence. LOG 260127-46 refers. SAP 8325301 refers. | U83: Under investigation, Unit 800205 was the Unit reported to be at fault, 801104 was stepped up to cover. | V83: Merge request sent to JP. JC 28/01 Merge request on hold while details are obtained. JC 28/01 | W83: MHB1 | X83: MHB1 | Y83: MD | AA83: D | AB83: New | AC83: Merged with Master | AE83: 260127-154459 | AG83: Merged | AH83: N | AI83: =IF(AD83="Availability", 0, IF(AND(AE83="Y", OR(J83>2, L83>0)), 1, 0)) -> 0 | AJ83: 701D | AK83: 2BM | AL83: =IFERROR(IF(AK83="", "", _xlfn.XLOOKUP(AK83, CODES!A:A,CODES!E:E)), "") -> LNER | AM83: =IFERROR(IF(AK83="", "", _xlfn.XLOOKUP(AK83, CODES!A:A,CODES!G:G)), "") -> Other | AN83: =IFERROR(IF(AK83="", "", _xlfn.XLOOKUP(AK83, CODES!A:A,CODES!I:I)), "") -> Merged - see Master | AO83: Merged with 153582.
A84: Root Cause | B84: 2611 | C84: 153582 | D84: 46049 | E84: 1A15 | F84: 09:37 BRADFORSQ to KINGS X | G84: AWK | H84: 13 | I84: 3 | J84: 13 | K84: 20 | L84: 3 | M84: 800204 | N84: 815204 | O84: 800204 | Q84: 5 | R84: 80x | S84: 43714 | T84: 1A15 13 LOST AWK DON TMS 5001 ETCS Double Computer Fault. LOG 260127-46 refers. SAP 8325301 refers. | U84: MTIN NO, HRE REJECT - Pulse Generator found to have sustained impact damage with confirmed water ingress when the component was inspected. Please see the photos attached. 800204 OPG - Last exam completed 11/01/26 | V84: To be accepted. JC 02/02 | W84: MHB1 | X84: MHB1 | Y84: M2 | Z84: M2 | AA84: A | AB84: Accepted | AC84: Accepted | AE84: 260127-153582 | AG84: Rejected | AH84: N | AI84: =IF(AD84="Availability", 0, IF(AND(AE84="Y", OR(J84>2, L84>0)), 1, 0)) -> 0 | AJ84: 701D | AK84: SEM | AL84: =IFERROR(IF(AK84="", "", _xlfn.XLOOKUP(AK84, CODES!A:A,CODES!E:E)), "") -> Safety System | AM84: =IFERROR(IF(AK84="", "", _xlfn.XLOOKUP(AK84, CODES!A:A,CODES!G:G)), "") -> ETCS | AN84: =IFERROR(IF(AK84="", "", _xlfn.XLOOKUP(AK84, CODES!A:A,CODES!I:I)), "") -> Pulse Generator | AO84: TMS 5001 ETCS Double Computer Fault. Impact damage found on the OPG casing, causing water ingress.
A85: Root Cause | B85: 2611 | C85: 153483 | D85: 46049 | E85: 1S09 | F85: 09:03 KINGS X to EDINBURGH | G85: PBO | H85: 4 | I85: 1 | J85: 4 | K85: 4 | L85: 2 | M85: 801214 | N85: 821214 | O85: 801214 | Q85: 9 | R85: 80x | S85: 43943 | T85: 1S09 4 OVERTIME PBO ETCS DMI Screen Blank or Distorted. LOG 260127-41 refers. SAP 8325270 refers. | U85: MTIN YES, HRE ACCEPT - ETCS DMI Screen replaced.. | W85: MHB2 | X85: MHB2 | Y85: M2 | Z85: M2 | AA85: A | AB85: Accepted | AC85: Accepted | AE85: 260127-153483 | AG85: Accepted | AH85: Y | AI85: =IF(AD85="Availability", 0, IF(AND(AE85="Y", OR(J85>2, L85>0)), 1, 0)) -> 0 | AJ85: 701D | AK85: SEH | AL85: =IFERROR(IF(AK85="", "", _xlfn.XLOOKUP(AK85, CODES!A:A,CODES!E:E)), "") -> Safety System | AM85: =IFERROR(IF(AK85="", "", _xlfn.XLOOKUP(AK85, CODES!A:A,CODES!G:G)), "") -> ETCS | AN85: =IFERROR(IF(AK85="", "", _xlfn.XLOOKUP(AK85, CODES!A:A,CODES!I:I)), "") -> ETCS DMI | AO85: ETCS DMI Screen Blank reported by driver. Screen renewed.
A86: Root Cause | B86: 2611 | C86: 153390 | D86: 46049 | E86: 1D05 | F86: 07:39 London Kings Cross - Bradford Forster Square | G86: DON | J86: 4 | K86: 4 | L86: 0 | M86: NL13 | N86: 10313 | O86: NL13 | Q86: 11 | R86: 225 | T86: 1D05 4 OVERTIME DON.....From Quartz "door fault in buffet car right side of travel" | W86: MHBB | X86: MHBB | Y86: M7 | Z86: M7 | AA86: A | AB86: Accepted | AC86: Report_Requested | AE86: 260127-153390 | AI86: =IF(AD86="Availability", 0, IF(AND(AE86="Y", OR(J86>2, L86>0)), 1, 0)) -> 0 | AJ86: 701D | AL86: =IFERROR(IF(AK86="", "", _xlfn.XLOOKUP(AK86, CODES!A:A,CODES!E:E)), "") | AM86: =IFERROR(IF(AK86="", "", _xlfn.XLOOKUP(AK86, CODES!A:A,CODES!G:G)), "") | AN86: =IFERROR(IF(AK86="", "", _xlfn.XLOOKUP(AK86, CODES!A:A,CODES!I:I)), "")
A87: Root Cause | B87: 2611 | C87: 153205 | D87: 46049 | E87: 3S08 | F87: 08:11 NEVHILL D to DONCASTER | G87: N/A | H87: 11 | I87: 0 | J87: 11 | K87: 15 | L87: 0 | M87: 801215 | O87: 801215 | Q87: 9 | R87: 80x | S87: 43843 | T87: 3S08 15 LATE START XNL 25/01 TIN 148853 incorrect merged with NR incident. New incident to reflet changes. TIN 148857 already merged into this incident. | U87: HRE Reject, MTIN – No. Depot report 3S08 held waiting for the signal to depart, due to Northern service 2T07 departing from Leeds. Class 3 only delay. | W87: MHBM | X87: MHBM | Y87: MU | Z87: MU | AA87: A | AB87: Accepted | AC87: Accepted | AE87: 260127-153205 | AG87: Rejected - Class 3/5 | AH87: N | AI87: =IF(AD87="Availability", 0, IF(AND(AE87="Y", OR(J87>2, L87>0)), 1, 0)) -> 0 | AJ87: 701A | AK87: 1BD | AL87: =IFERROR(IF(AK87="", "", _xlfn.XLOOKUP(AK87, CODES!A:A,CODES!E:E)), "") -> Operational | AM87: =IFERROR(IF(AK87="", "", _xlfn.XLOOKUP(AK87, CODES!A:A,CODES!G:G)), "") -> Depot | AN87: =IFERROR(IF(AK87="", "", _xlfn.XLOOKUP(AK87, CODES!A:A,CODES!I:I)), "") -> Process | AO87: Unit late off depot.
A88: Root Cause | B88: 2611 | C88: 152900 | D88: 46049 | E88: 1E02 | F88: 05:50 EDINBURGH to KINGS X | G88: BWK BELFORD | H88: 83 | I88: 1 | J88: 94 | K88: 345 | L88: 1 | M88: 801227 | N88: 824227 | O88: 801227 | Q88: 9 | R88: 80x | S88: 43957 | T88: 1E02 47 LOST BWK BELFORD The Driver of 1E02 0550 Edinburgh to Kings Cross advised the Hitachi Maintenance Controller that the service was stood on the up main line at Goswick with a WSP and BCU indication. LOG 260127-36 refers. SAP 8325108 refers - TMS 4401 BCU Fault. | U88: MTIN YES, HRE ACCEPT - LAD10 and LAD05 cards renewed. | V88: 83 mins and part canx for 1E02. JC 30/01 | W88: MHB2 | X88: MHB2 | Y88: MN | Z88: MN | AA88: A | AB88: Accepted | AC88: Accepted | AE88: 260127-152900 | AG88: Accepted | AH88: Y | AI88: =IF(AD88="Availability", 0, IF(AND(AE88="Y", OR(J88>2, L88>0)), 1, 0)) -> 0 | AJ88: 701D | AK88: BBH | AL88: =IFERROR(IF(AK88="", "", _xlfn.XLOOKUP(AK88, CODES!A:A,CODES!E:E)), "") -> Brake System | AM88: =IFERROR(IF(AK88="", "", _xlfn.XLOOKUP(AK88, CODES!A:A,CODES!G:G)), "") -> Brake Control Unit | AN88: =IFERROR(IF(AK88="", "", _xlfn.XLOOKUP(AK88, CODES!A:A,CODES!I:I)), "") -> LAD10F Control Board | AO88: WSP and BCU faults reported by driver. LAD10 and LAD05 cards renewed.
A89: Root Cause | B89: 2611 | C89: 152814 | D89: 46049 | E89: 1Y01 | F89: 04:40 York - London Kings Cross | G89: PBO | J89: 6 | K89: 6 | L89: 0 | M89: NL13 | N89: 10313 | O89: NL13 | Q89: 11 | R89: 225 | T89: 1Y01 6 OVERTIME PBO…..From Quartz "Interlock issue with coach H north end door, multiple dispatch attempts and panel change from TM eventually resolved the issue and achieved the interlock" | W89: MHBB | X89: MHBB | Y89: M7 | Z89: M7 | AA89: A | AB89: Accepted | AC89: Report_Requested | AE89: 260127-152814 | AI89: =IF(AD89="Availability", 0, IF(AND(AE89="Y", OR(J89>2, L89>0)), 1, 0)) -> 0 | AJ89: 701D | AL89: =IFERROR(IF(AK89="", "", _xlfn.XLOOKUP(AK89, CODES!A:A,CODES!E:E)), "") | AM89: =IFERROR(IF(AK89="", "", _xlfn.XLOOKUP(AK89, CODES!A:A,CODES!G:G)), "") | AN89: =IFERROR(IF(AK89="", "", _xlfn.XLOOKUP(AK89, CODES!A:A,CODES!I:I)), "")
A90: Root Cause | B90: 2611 | C90: 152718 | D90: 46049 | E90: 5A05 | F90: 05:35 Neville Hill T&R.S.M.D - Leeds | G90: XNL | J90: 5 | K90: 5 | L90: 0 | M90: NL08 | O90: NL08 | Q90: 11 | R90: 225 | T90: 5A05 5 LATE START XNL | U90: Following late departure | V90: Following late departure | W90: MHBM | X90: MHBM | Y90: MU | AA90: A | AB90: New | AC90: Accepted | AE90: 260127-152718 | AH90: N | AI90: =IF(AD90="Availability", 0, IF(AND(AE90="Y", OR(J90>2, L90>0)), 1, 0)) -> 0 | AJ90: 701A | AL90: =IFERROR(IF(AK90="", "", _xlfn.XLOOKUP(AK90, CODES!A:A,CODES!E:E)), "") | AM90: =IFERROR(IF(AK90="", "", _xlfn.XLOOKUP(AK90, CODES!A:A,CODES!G:G)), "") | AN90: =IFERROR(IF(AK90="", "", _xlfn.XLOOKUP(AK90, CODES!A:A,CODES!I:I)), "")
A91: Root Cause | B91: 2611 | C91: 152711 | D91: 46049 | E91: 3A10 | F91: 05:25 Neville Hill T&R.S.M.D - Skipton | G91: XNL | J91: 3 | K91: 3 | L91: 0 | M91: NL26 | O91: NL26 | Q91: 11 | R91: 225 | T91: 3A10 3 LATE START XNL | U91: Following late departure | V91: Following late departure | W91: MHBM | X91: MHBM | Y91: MU | AA91: A | AB91: New | AC91: Accepted | AE91: 260127-152711 | AH91: N | AI91: =IF(AD91="Availability", 0, IF(AND(AE91="Y", OR(J91>2, L91>0)), 1, 0)) -> 0 | AJ91: 701A | AL91: =IFERROR(IF(AK91="", "", _xlfn.XLOOKUP(AK91, CODES!A:A,CODES!E:E)), "") | AM91: =IFERROR(IF(AK91="", "", _xlfn.XLOOKUP(AK91, CODES!A:A,CODES!G:G)), "") | AN91: =IFERROR(IF(AK91="", "", _xlfn.XLOOKUP(AK91, CODES!A:A,CODES!I:I)), "")
A92: Root Cause | B92: 2611 | C92: 152306 | D92: 46048 | E92: 1N35 | G92: KGX | J92: 13 | K92: 13 | L92: 0 | M92: NL13 | O92: NL13 | Q92: 11 | R92: 225 | T92: 1N35 13 LATE START KGX | W92: MHBC | X92: MHBC | Y92: M7 | Z92: M7 | AA92: A | AB92: Accepted | AC92: Investigation | AE92: 260126-152306 | AI92: =IF(AD92="Availability", 0, IF(AND(AE92="Y", OR(J92>2, L92>0)), 1, 0)) -> 0 | AJ92: 701D | AL92: =IFERROR(IF(AK92="", "", _xlfn.XLOOKUP(AK92, CODES!A:A,CODES!E:E)), "") | AM92: =IFERROR(IF(AK92="", "", _xlfn.XLOOKUP(AK92, CODES!A:A,CODES!G:G)), "") | AN92: =IFERROR(IF(AK92="", "", _xlfn.XLOOKUP(AK92, CODES!A:A,CODES!I:I)), "")
A93: Root Cause | B93: 2611 | C93: 152025 | D93: 46048 | E93: 1D26 | F93: 18:03 KINGS X to SKIPTON | G93: LDS | H93: 0 | I93: 0.5 | J93: 0 | K93: 30 | L93: 0.5 | M93: 800/801 | N93: 811201 | O93: 800201 | P93: 801107 | Q93: 5 | R93: 80x | S93: 43735 | T93: 1D26 CANCELLED LDS SKI TRI called at 20:52 to say unable to electrically uncouple so de trained. TRI called at 21:05 to say they were going to take a block to manually retract electrical coupler heads. TRI called at 21:18 to say units un coupled. LOG 260126-48 refers. SAP 8324301 refers - Unable to mechanically uncouple | U93: MTIN YES, HRE ACCEPT - M/Human error, ACIC found to be in incorrect position, QN to be raised. | W93: MHB2 | X93: MHB2 | Y93: MY | Z93: MY | AA93: A | AB93: Accepted | AC93: Accepted | AE93: 260126-152025 | AG93: Accepted | AH93: Y | AI93: =IF(AD93="Availability", 0, IF(AND(AE93="Y", OR(J93>2, L93>0)), 1, 0)) -> 0 | AJ93: 701D | AK93: AE7 | AL93: =IFERROR(IF(AK93="", "", _xlfn.XLOOKUP(AK93, CODES!A:A,CODES!E:E)), "") -> Air System | AM93: =IFERROR(IF(AK93="", "", _xlfn.XLOOKUP(AK93, CODES!A:A,CODES!G:G)), "") -> Isolation Cocks, Valves & Pipes | AN93: =IFERROR(IF(AK93="", "", _xlfn.XLOOKUP(AK93, CODES!A:A,CODES!I:I)), "") -> Non Technical | AO93: Issues when trying to couple train. ACIC found to be in the incorrect position.
A94: Root Cause | B94: 2611 | C94: 151124 | D94: 46048 | E94: 1D12 | G94: WKF WHRDJN | J94: 3 | K94: 3 | L94: 0 | M94: NL06 | O94: NL06 | Q94: 11 | R94: 225 | T94: 1D12 3 LOST WKF WHRDJN | W94: MHBA | X94: MHBA | Y94: MP | Z94: MP | AA94: A | AB94: Accepted | AC94: Investigation | AE94: 260126-151124 | AI94: =IF(AD94="Availability", 0, IF(AND(AE94="Y", OR(J94>2, L94>0)), 1, 0)) -> 0 | AJ94: 750 | AL94: =IFERROR(IF(AK94="", "", _xlfn.XLOOKUP(AK94, CODES!A:A,CODES!E:E)), "") | AM94: =IFERROR(IF(AK94="", "", _xlfn.XLOOKUP(AK94, CODES!A:A,CODES!G:G)), "") | AN94: =IFERROR(IF(AK94="", "", _xlfn.XLOOKUP(AK94, CODES!A:A,CODES!I:I)), "")
A95: Root Cause | B95: 2611 | C95: 150832 | D95: 46048 | E95: 5E10 | F95: 09:14 CRAIGNTNY to EDINBURGH | G95: XCN | H95: 2 | I95: 0 | J95: 2 | K95: 3 | L95: 0 | M95: 801218 | O95: 801218 | Q95: 9 | R95: 80x | S95: 43998 | T95: 5E10 2 LATE START XCN L2 TMV SHOWS 5E10 HAVING 2 MINS LATE START. NO SUPPORTING INFO ON TAS. | U95: Depot report waiting for the signal to depart. | V95: 5E10 0914 CRAIGNTNY to EDINBURGH presented at 09:15:42. | W95: MHBK | X95: MHBK | Y95: MU | Z95: MU | AA95: A | AB95: Accepted | AC95: Accepted | AE95: 260126-150832 | AG95: Rejected - Class 3/5 | AH95: N | AI95: =IF(AD95="Availability", 0, IF(AND(AE95="Y", OR(J95>2, L95>0)), 1, 0)) -> 0 | AJ95: 701A | AK95: 1BD | AL95: =IFERROR(IF(AK95="", "", _xlfn.XLOOKUP(AK95, CODES!A:A,CODES!E:E)), "") -> Operational | AM95: =IFERROR(IF(AK95="", "", _xlfn.XLOOKUP(AK95, CODES!A:A,CODES!G:G)), "") -> Depot | AN95: =IFERROR(IF(AK95="", "", _xlfn.XLOOKUP(AK95, CODES!A:A,CODES!I:I)), "") -> Process | AO95: Unit late off depot.
A96: Removed - Reassigned | B96: 2611 | C96: 150790 | D96: 46048 | E96: 1E11 | F96: 07:52 ABERDEEN to KINGS X | G96: INK | H96: 10 | I96: 0 | J96: 10 | K96: 21 | L96: 0 | M96: 800105 | N96: 819105 | O96: 800105 | Q96: 9 | R96: 80x | S96: 43572 | T96: 1E11 7 LOST INK DALMINYJN AWS/TPWSD brake demand received for 1E11 on the up main line at Dalgety Bay. STSM reports vis driver manager that set within LNER tolerance OTMR shows 1.4mph overspeed and no allegation against set. LOG 260126-36 refers. SAP 8323191 refers - TMS 0103 AWS/TPWS Brake Applied | U96: HRE Reject, MTIN – No. Confirmed Driver overspeed, please see the report attached for further details. | V96: Referral request sent to DR. JC 27/01 | W96: THB4 | X96: THB4 | Y96: TG | Z96: TG | AA96: A | AB96: Accepted | AC96: Referred | AE96: 260126-150790 | AG96: Rejected | AH96: N | AI96: =IF(AD96="Availability", 0, IF(AND(AE96="Y", OR(J96>2, L96>0)), 1, 0)) -> 0 | AJ96: 701C | AK96: 1AA | AL96: =IFERROR(IF(AK96="", "", _xlfn.XLOOKUP(AK96, CODES!A:A,CODES!E:E)), "") -> Operational | AM96: =IFERROR(IF(AK96="", "", _xlfn.XLOOKUP(AK96, CODES!A:A,CODES!G:G)), "") -> Staff | AN96: =IFERROR(IF(AK96="", "", _xlfn.XLOOKUP(AK96, CODES!A:A,CODES!I:I)), "") -> Driver | AO96: Operational error by driver, AWS/TPWSD brake demand due to overspeed.
A97: Root Cause | B97: 2611 | C97: 150738 | D97: 46048 | E97: 1A32 | G97: DON | J97: 3 | K97: 15 | L97: 0 | M97: NL15 | O97: NL15 | Q97: 11 | R97: 225 | T97: 1A32 3 OVERTIME DON 23/01 | U97: DVT door jammed shut? | W97: MHBC | X97: MHBC | Y97: M7 | Z97: M7 | AA97: A | AB97: Accepted | AC97: Investigation | AE97: 260126-150738 | AI97: =IF(AD97="Availability", 0, IF(AND(AE97="Y", OR(J97>2, L97>0)), 1, 0)) -> 0 | AJ97: 701D | AL97: =IFERROR(IF(AK97="", "", _xlfn.XLOOKUP(AK97, CODES!A:A,CODES!E:E)), "") | AM97: =IFERROR(IF(AK97="", "", _xlfn.XLOOKUP(AK97, CODES!A:A,CODES!G:G)), "") | AN97: =IFERROR(IF(AK97="", "", _xlfn.XLOOKUP(AK97, CODES!A:A,CODES!I:I)), "")
A98: Removed - Reassigned | B98: 2611 | C98: 150048 | D98: 46048 | E98: 5S28 | F98: 23:19 EDINBURGH to CRAIGNTNY | G98: EDB XCN | H98: 1 | I98: 0 | J98: 1 | K98: 1 | L98: 0 | M98: 800112 | O98: 800112 | Q98: 9 | R98: 80x | S98: 43536 | T98: 5S28 LOST EDB CRGNTNY Awaiting accept onto depot. | U98: Not attributable. | W98: NROP | X98: ZQLB | Y98: ZS | AA98: A | AB98: New | AC98: Referred | AE98: 260126-150048 | AG98: Rejected - Sub Threshold | AH98: N | AI98: =IF(AD98="Availability", 0, IF(AND(AE98="Y", OR(J98>2, L98>0)), 1, 0)) -> 0 | AJ98: 601 | AK98: 1DB | AL98: =IFERROR(IF(AK98="", "", _xlfn.XLOOKUP(AK98, CODES!A:A,CODES!E:E)), "") -> Operational | AM98: =IFERROR(IF(AK98="", "", _xlfn.XLOOKUP(AK98, CODES!A:A,CODES!G:G)), "") -> NR | AN98: =IFERROR(IF(AK98="", "", _xlfn.XLOOKUP(AK98, CODES!A:A,CODES!I:I)), "") -> Regulation | AO98: Awaiting acceptance onto depot.
A99: Root Cause | B99: 2611 | C99: 150029 | D99: 46048 | E99: 5Y26 | F99: 23:04 KINGS X to BOUNDGNCS | G99: XGD | H99: 6 | I99: 0 | J99: 6 | K99: 12 | L99: 0 | M99: 801228 | O99: 801228 | Q99: 9 | R99: 80x | S99: 43964 | T99: 5Y26 DEPOT OPS XGD Awaiting access onto depot. | U99: HRE Reject, MTIN – No. Depot report Unit arrived +5 minutes late at Bowes Park, waiting for 2B77 and then 1T69 to clear Bowes Park Platform 1. Class 5 only delay. | W99: MHBJ | X99: MHBJ | Y99: MU | Z99: MU | AA99: A | AB99: Accepted | AC99: Accepted | AE99: 260126-150029 | AG99: Rejected - Sub Threshold | AH99: N | AI99: =IF(AD99="Availability", 0, IF(AND(AE99="Y", OR(J99>2, L99>0)), 1, 0)) -> 0 | AJ99: 701A | AK99: 1BB | AL99: =IFERROR(IF(AK99="", "", _xlfn.XLOOKUP(AK99, CODES!A:A,CODES!E:E)), "") -> Operational | AM99: =IFERROR(IF(AK99="", "", _xlfn.XLOOKUP(AK99, CODES!A:A,CODES!G:G)), "") -> Depot | AN99: =IFERROR(IF(AK99="", "", _xlfn.XLOOKUP(AK99, CODES!A:A,CODES!I:I)), "") -> Awaiting Acceptance | AO99: Awaiting acceptance onto depot.
A100: Merged | B100: 2611 | C100: 148995 | D100: 46047 | F100: 10:15 KINGS X to EDINBURGH | G100: KGX | H100: 7 | I100: 0 | J100: 7 | K100: 14 | L100: 0 | M100: 801227 | O100: 801227 | Q100: 9 | R100: 80x | S100: 43957 | T100: 1S12 UNIT SWAP KGX SET SWAP DUE TO LATE OFF DEPOT 5S12. MERGE TO 148982 5S12 61 LATE START XFD. YI TO 5S12 | U100: Related to 5S12 TIN 148982 below. | V100: Merge request sent. JC 26/01 | W100: MHBJ | X100: MHBJ | Y100: MS | AA100: D | AB100: New | AC100: Merged with Master | AE100: 260125-148995 | AG100: Merged | AH100: N | AI100: =IF(AD100="Availability", 0, IF(AND(AE100="Y", OR(J100>2, L100>0)), 1, 0)) -> 0 | AJ100: 701A | AK100: 2BM | AL100: =IFERROR(IF(AK100="", "", _xlfn.XLOOKUP(AK100, CODES!A:A,CODES!E:E)), "") -> LNER | AM100: =IFERROR(IF(AK100="", "", _xlfn.XLOOKUP(AK100, CODES!A:A,CODES!G:G)), "") -> Other | AN100: =IFERROR(IF(AK100="", "", _xlfn.XLOOKUP(AK100, CODES!A:A,CODES!I:I)), "") -> Merged - see Master | AO100: Merged with 148982.
...

Sheet LOOKUPS
A1: LNER_Fleet_Status | B1: Who_Accepted | C1: Who_Referred | D1: Who_Requested | E1: Waiting_Att_Mgr_Decision | F1: Wtg_Referral_Dec | G1: Hitachi_Status | H1: Yes_No | I1: Vehicle_No | J1: Unit_No
A2: Investigation | B2: Fleet | C2: 225 Fleet Tech | D2: Driver | E2: Driver Error | F2: 225 Fleet Tech | G2: Investigation | H2: Y | I2: 811101 | J2: 800101
A3: Accepted | B3: Other | C3: TM | D3: TM | E3: TM Error | F3: TM | G3: Accepted | H3: N | I3: 811102 | J3: 800102
A4: Referred | B4: 225 Depot | C4: Driver | D4: Station | E4: Driver Door Obstacle | F4: Driver | G4: Availability | I4: 811103 | J4: 800103
A5: Report_Requested | C5: Station | D5: Onboard | E5: Passengers | F5: Station | G5: Merged | I5: 811104 | J5: 800104
A6: Merged with Master | C6: NR | D6: HRL | E6: Incorrect Dispatch | F6: NR | G6: TOC Dispute | I6: 811105 | J6: 800105
A7: Refer to Level 2 | C7: Control | D7: Ops | E7: Incident not Reported to MC | F7: Control | G7: Rejected - Class 3/5 | I7: 811106 | J7: 800106
A8: Wtg_Att_Mgr_Dec | C8: Other | D8: NR | E8: Awaiting Stoke Tech | F8: Other | G8: Rejected - Unsold Unit | I8: 811107 | J8: 800107
A9: Wtg_Referral_Dec | C9: Vandalism | E9: Awaiting CCF to Review | F9: Vandalism | G9: Rejected - Sub Threshold | I9: 811108 | J9: 800108
A10: Discuss with HRL | E10: Awaiting NR | F10: Awaiting DRV Report | G10: Rejected - 225 delay | I10: 811109 | J10: 800109
E11: Awaiting Amendment TRUST/Bugle Code | F11: Awaiting DTM to Review | G11: Rejected | I11: 811110 | J11: 800110
E12: Awaiting Attribution Decision | F12: Awaiting TM Report | I12: 811111 | J12: 800111
F13: Awaiting Referral Acceptance | I13: 811112 | J13: 800112
I14: 811113 | J14: 800113
I15: 812101 | J15: 800201
I16: 812102 | J16: 800202
I17: 812103 | J17: 800203
I18: 812104 | J18: 800204
I19: 812105 | J19: 800205
I20: 812106 | J20: 800206
I21: 812107 | J21: 800207
I22: 812108 | J22: 800208
I23: 812109 | J23: 800209
I24: 812110 | J24: 800210
I25: 812111 | J25: 801101
... I75: 816109 | J75: undefined
I76: 816110
I77: 816111
I78: 816112
I79: 816113
I80: 817101
I81: 817102
I82: 817103
I83: 817104
I84: 817105
I85: 817106
I86: 817107
I87: 817108
... I592: 91130

Sheet CODES
A1: Code | B1: System_SubSystem_Component | C1: Safety_Critical | D1: System_Code | E1: System | F1: SubSystem_Code | G1: SubSystem | H1: Component_Code | I1: Component | J1: Fleet
A2: 1A9 | B2: Operational_Staff_No Fault Identified | C2: N | D2: 1 | E2: Operational | F2: A | G2: Staff | H2: 9 | I2: No Fault Identified | J2: Azuma
A3: 1AA | B3: Operational_Staff_Driver | C3: N | D3: 1 | E3: Operational | F3: A | G3: Staff | H3: A | I3: Driver | J3: Azuma
A4: 1AB | B4: Operational_Staff_TM | C4: N | D4: 1 | E4: Operational | F4: A | G4: Staff | H4: B | I4: TM | J4: Azuma
A5: 1AC | B5: Operational_Staff_Train Crew | C5: N | D5: 1 | E5: Operational | F5: A | G5: Staff | H5: C | I5: Train Crew | J5: Azuma
A6: 1AD | B6: Operational_Staff_Platform | C6: N | D6: 1 | E6: Operational | F6: A | G6: Staff | H6: D | I6: Platform | J6: Azuma
A7: 1AE | B7: Operational_Staff_Other | C7: N | D7: 1 | E7: Operational | F7: A | G7: Staff | H7: E | I7: Other | J7: Azuma
A8: 1B9 | B8: Operational_Depot_No Fault Identified | C8: N | D8: 1 | E8: Operational | F8: B | G8: Depot | H8: 9 | I8: No Fault Identified | J8: Azuma
A9: 1BA | B9: Operational_Depot_InfraStructure | C9: N | D9: 1 | E9: Operational | F9: B | G9: Depot | H9: A | I9: InfraStructure | J9: Azuma
A10: 1BB | B10: Operational_Depot_Awaiting Acceptance | C10: N | D10: 1 | E10: Operational | F10: B | G10: Depot | H10: B | I10: Awaiting Acceptance | J10: Azuma
A11: 1BC | B11: Operational_Depot_Planning | C11: N | D11: 1 | E11: Operational | F11: B | G11: Depot | H11: C | I11: Planning | J11: Azuma
A12: 1BD | B12: Operational_Depot_Process | C12: N | D12: 1 | E12: Operational | F12: B | G12: Depot | H12: D | I12: Process | J12: Azuma
... A88: 225-2BN | B88: LNER_Other_Passenger Vandalism | C88: N | D88: 2 | E88: LNER | F88: B | G88: Other | H88: N | I88: Passenger Vandalism | J88: 225
A89: 225-AA1 | B89: Air System_Control_No Fault Identified | D89: A | E89: Air System | F89: A | G89: Control | H89: 1 | I89: No Fault Identified | J89: 225
A90: 225-AAA | B90: Air System_Control_Contactor Single phase | D90: A | E90: Air System | F90: A | G90: Control | H90: A | I90: Contactor Single phase | J90: 225
A91: 225-AAB | B91: Air System_Control_Contactor three phase | D91: A | E91: Air System | F91: A | G91: Control | H91: B | I91: Contactor three phase | J91: 225
A92: 225-AAC | B92: Air System_Control_Contactor - Change over | D92: A | E92: Air System | F92: A | G92: Control | H92: C | I92: Contactor - Change over | J92: 225
A93: 225-AAD | B93: Air System_Control_Contactor coil | D93: A | E93: Air System | F93: A | G93: Control | H93: D | I93: Contactor coil | J93: 225
A94: 225-AAE | B94: Air System_Control_Contactor fixed tip | D94: A | E94: Air System | F94: A | G94: Control | H94: E | I94: Contactor fixed tip | J94: 225
A95: 225-AAF | B95: Air System_Control_Contactor moving tip | D95: A | E95: Air System | F95: A | G95: Control | H95: F | I95: Contactor moving tip | J95: 225
A96: 225-AAG | B96: Air System_Control_Knuckle Spring | D96: A | E96: Air System | F96: A | G96: Control | H96: G | I96: Knuckle Spring | J96: 225
A97: 225-AAH | B97: Air System_Control_Terminal Connections | D97: A | E97: Air System | F97: A | G97: Control | H97: H | I97: Terminal Connections | J97: 225
A98: 225-AAI | B98: Air System_Control_Terminal fasteners | D98: A | E98: Air System | F98: A | G98: Control | H98: I | I98: Terminal fasteners | J98: 225
A99: 225-AAJ | B99: Air System_Control_Arc Chute | D99: A | E99: Air System | F99: A | G99: Control | H99: J | I99: Arc Chute | J99: 225
A100: 225-AAK | B100: Air System_Control_Wiring | D100: A | E100: Air System | F100: A | G100: Control | H100: K | I100: Wiring | J100: 225
... A2753: 225-ZFH | B2753: Equipment_Portable Fire_Fire Blanket (catering) | D2753: Z | E2753: Equipment | F2753: F | G2753: Portable Fire | H2753: H | I2753: Fire Blanket (catering) | J2753: 225
A2754: AA6 | B2754: Air System_Air Horn_Fault not Investigated | C2754: Y | D2754: A | E2754: Air System | F2754: A | G2754: Air Horn | H2754: 6 | I2754: Fault not Investigated | J2754: Azuma
A2755: AA7 | B2755: Air System_Air Horn_Non Technical | C2755: Y | D2755: A | E2755: Air System | F2755: A | G2755: Air Horn | H2755: 7 | I2755: Non Technical | J2755: Azuma
A2756: AA8 | B2756: Air System_Air Horn_Operator | C2756: Y | D2756: A | E2756: Air System | F2756: A | G2756: Air Horn | H2756: 8 | I2756: Operator | J2756: Azuma
A2757: AA9 | B2757: Air System_Air Horn_No Fault Identified | C2757: Y | D2757: A | E2757: Air System | F2757: A | G2757: Air Horn | H2757: 9 | I2757: No Fault Identified | J2757: Azuma
A2758: AAA | B2758: Air System_Air Horn_EP Valve | C2758: Y | D2758: A | E2758: Air System | F2758: A | G2758: Air Horn | H2758: A | I2758: EP Valve | J2758: Azuma
A2759: AAB | B2759: Air System_Air Horn_Horn | C2759: Y | D2759: A | E2759: Air System | F2759: A | G2759: Air Horn | H2759: B | I2759: Horn | J2759: Azuma
A2760: AAC | B2760: Air System_Air Horn_Horn Pressure Switch | C2760: Y | D2760: A | E2760: Air System | F2760: A | G2760: Air Horn | H2760: C | I2760: Horn Pressure Switch | J2760: Azuma
A2761: AAD | B2761: Air System_Air Horn_Lever Operated Horn Valve | C2761: Y | D2761: A | E2761: Air System | F2761: A | G2761: Air Horn | H2761: D | I2761: Lever Operated Horn Valve | J2761: Azuma
A2762: AAE | B2762: Air System_Air Horn_Pipework | C2762: Y | D2762: A | E2762: Air System | F2762: A | G2762: Air Horn | H2762: E | I2762: Pipework | J2762: Azuma
A2763: AAF | B2763: Air System_Air Horn_Regulator | C2763: Y | D2763: A | E2763: Air System | F2763: A | G2763: Air Horn | H2763: F | I2763: Regulator | J2763: Azuma
A2764: AAG | B2764: Air System_Air Horn_Thermostatic Junction Box | C2764: Y | D2764: A | E2764: Air System | F2764: A | G2764: Air Horn | H2764: G | I2764: Thermostatic Junction Box | J2764: Azuma
A2765: AAH | B2765: Air System_Air Horn_Adverse Weather | C2765: Y | D2765: A | E2765: Air System | F2765: A | G2765: Air Horn | H2765: H | I2765: Adverse Weather | J2765: Azuma
... A2870: BCC | B2870: Brake System_Cab & Vestibule Equipment_Brake Coding MCB | C2870: Y | D2870: B | E2870: Brake System | F2870: C | G2870: Cab & Vestibule Equipment | H2870: C | I2870: Brake Coding MCB | J2870: Azuma
A2871: C8 | B2871: Water and Toilet Systems_SST Toilet Door_Operator | C2871: N | E2871: Water and Toilet Systems | F2871: C | G2871: SST Toilet Door | H2871: 8 | I2871: Operator | J2871: Azuma
A2872: C9 | B2872: Water and Toilet Systems_SST Toilet Door_No Fault Identified | C2872: N | E2872: Water and Toilet Systems | F2872: C | G2872: SST Toilet Door | H2872: 9 | I2872: No Fault Identified | J2872: Azuma
A2873: CA6 | B2873: Bodyshell and Exterior_Body End_Fault not Investigated | C2873: Y | D2873: C | E2873: Bodyshell and Exterior | F2873: A | G2873: Body End | H2873: 6 | I2873: Fault not Investigated | J2873: Azuma
A2874: CA7 | B2874: Bodyshell and Exterior_Body End_Non Technical | C2874: Y | D2874: C | E2874: Bodyshell and Exterior | F2874: A | G2874: Body End | H2874: 7 | I2874: Non Technical | J2874: Azuma
A2875: CA8 | B2875: Bodyshell and Exterior_Body End_Operator | C2875: Y | D2875: C | E2875: Bodyshell and Exterior | F2875: A | G2875: Body End | H2875: 8 | I2875: Operator | J2875: Azuma
A2876: CA9 | B2876: Bodyshell and Exterior_Body End_No Fault Identified | C2876: Y | D2876: C | E2876: Bodyshell and Exterior | F2876: A | G2876: Body End | H2876: 9 | I2876: No Fault Identified | J2876: Azuma
A2877: CAA | B2877: Bodyshell and Exterior_Body End_Anti Climb | C2877: Y | D2877: C | E2877: Bodyshell and Exterior | F2877: A | G2877: Body End | H2877: A | I2877: Anti Climb | J2877: Azuma
A2878: CAB | B2878: Bodyshell and Exterior_Body End_Cab Entrance Steps | C2878: Y | D2878: C | E2878: Bodyshell and Exterior | F2878: A | G2878: Body End | H2878: B | I2878: Cab Entrance Steps | J2878: Azuma
A2879: CAC | B2879: Bodyshell and Exterior_Body End_Emergency Head Lamp Bracket | C2879: Y | D2879: C | E2879: Bodyshell and Exterior | F2879: A | G2879: Body End | H2879: C | I2879: Emergency Head Lamp Bracket | J2879: Azuma
A2880: CAD | B2880: Bodyshell and Exterior_Body End_Front Mask | C2880: Y | D2880: C | E2880: Bodyshell and Exterior | F2880: A | G2880: Body End | H2880: D | I2880: Front Mask | J2880: Azuma
A2881: CAE | B2881: Bodyshell and Exterior_Body End_Head & Tail Light Cover | C2881: Y | D2881: C | E2881: Bodyshell and Exterior | F2881: A | G2881: Body End | H2881: E | I2881: Head & Tail Light Cover | J2881: Azuma
A2882: CAF | B2882: Bodyshell and Exterior_Body End_Nose End Skirt | C2882: Y | D2882: C | E2882: Bodyshell and Exterior | F2882: A | G2882: Body End | H2882: F | I2882: Nose End Skirt | J2882: Azuma
A2883: CAG | B2883: Bodyshell and Exterior_Body End_Obstacle Deflector | C2883: Y | D2883: C | E2883: Bodyshell and Exterior | F2883: A | G2883: Body End | H2883: G | I2883: Obstacle Deflector | J2883: Azuma
A2884: CAH | B2884: Bodyshell and Exterior_Body End_RFID Tag | C2884: Y | D2884: C | E2884: Bodyshell and Exterior | F2884: A | G2884: Body End | H2884: H | I2884: RFID Tag | J2884: Azuma
... A4220: XBD | B4220: Communication Systems_CCTV_CCTV Network Unit | C4220: N | D4220: X | E4220: Communication Systems | F4220: B | G4220: CCTV | H4220: D | I4220: CCTV Network Unit | J4220: Azuma
A4221: XBE | B4221: Communication Systems_CCTV_ | C4221: N | D4221: X | E4221: Communication Systems | F4221: B | G4221: CCTV | H4221: E | J4221: Azuma
A4222: XBF | B4222: Communication Systems_CCTV_CCTV Power Unit | C4222: N | D4222: X | E4222: Communication Systems | F4222: B | G4222: CCTV | H4222: F | I4222: CCTV Power Unit | J4222: Azuma
A4223: XBG | B4223: Communication Systems_CCTV_DOO Camera | C4223: N | D4223: X | E4223: Communication Systems | F4223: B | G4223: CCTV | H4223: G | I4223: DOO Camera | J4223: Azuma
A4224: XBH | B4224: Communication Systems_CCTV_Forward Facing Camera | C4224: N | D4224: X | E4224: Communication Systems | F4224: B | G4224: CCTV | H4224: H | I4224: Forward Facing Camera | J4224: Azuma
A4225: XBI | B4225: Communication Systems_CCTV_HDD Cartridge | C4225: N | D4225: X | E4225: Communication Systems | F4225: B | G4225: CCTV | H4225: I | I4225: HDD Cartridge | J4225: Azuma
A4226: XBJ | B4226: Communication Systems_CCTV_Network Digital Recorder | C4226: N | D4226: X | E4226: Communication Systems | F4226: B | G4226: CCTV | H4226: J | I4226: Network Digital Recorder | J4226: Azuma
A4227: XBK | B4227: Communication Systems_CCTV_Pantograph Camera Pod | C4227: N | D4227: X | E4227: Communication Systems | F4227: B | G4227: CCTV | H4227: K | I4227: Pantograph Camera Pod | J4227: Azuma
A4228: XBL | B4228: Communication Systems_CCTV_Saloon Camera | C4228: N | D4228: X | E4228: Communication Systems | F4228: B | G4228: CCTV | H4228: L | I4228: Saloon Camera | J4228: Azuma
A4229: XBM | B4229: Communication Systems_CCTV_Software | C4229: N | D4229: X | E4229: Communication Systems | F4229: B | G4229: CCTV | H4229: M | I4229: Software | J4229: Azuma
A4230: XBN | B4230: Communication Systems_CCTV_Switching HUB | C4230: N | D4230: X | E4230: Communication Systems | F4230: B | G4230: CCTV | H4230: N | I4230: Switching HUB | J4230: Azuma
A4231: XBO | B4231: Communication Systems_CCTV_Vestibule Camera | C4231: N | D4231: X | E4231: Communication Systems | F4231: B | G4231: CCTV | H4231: O | I4231: Vestibule Camera | J4231: Azuma
A4232: XBP | B4232: Communication Systems_CCTV_Wiring/Plugs | C4232: Y | D4232: X | E4232: Communication Systems | F4232: B | G4232: CCTV | H4232: P | I4232: Wiring/Plugs | J4232: Azuma
A4233: XC6 | B4233: Communication Systems_GSM R_Fault not Investigated | C4233: Y | D4233: X | E4233: Communication Systems | F4233: C | G4233: GSM R | H4233: 6 | I4233: Fault not Investigated | J4233: Azuma
... A4337: ZCL | B4337: Emergency Equipment_Recovery & First Aid Equipment_First Aid Box | C4337: N | D4337: Z | E4337: Emergency Equipment | F4337: C | G4337: Recovery & First Aid Equipment | H4337: L | I4337: First Aid Box | J4337: Azuma
A4338: ZCM | B4338: Emergency Equipment_Recovery & First Aid Equipment_ | C4338: N | D4338: Z | E4338: Emergency Equipment | F4338: C | G4338: Recovery & First Aid Equipment | H4338: M | J4338: Azuma
A4339: ZCN | B4339: Emergency Equipment_Recovery & First Aid Equipment_Foil Blanket | C4339: N | D4339: Z | E4339: Emergency Equipment | F4339: C | G4339: Recovery & First Aid Equipment | H4339: N | I4339: Foil Blanket | J4339: Azuma
A4340: ZCO | B4340: Emergency Equipment_Recovery & First Aid Equipment_Gauntlet Gloves | C4340: N | D4340: Z | E4340: Emergency Equipment | F4340: C | G4340: Recovery & First Aid Equipment | H4340: O | I4340: Gauntlet Gloves | J4340: Azuma
A4341: ZCP | B4341: Emergency Equipment_Recovery & First Aid Equipment_Hand Axe | C4341: N | D4341: Z | E4341: Emergency Equipment | F4341: C | G4341: Recovery & First Aid Equipment | H4341: P | I4341: Hand Axe | J4341: Azuma
A4342: ZCQ | B4342: Emergency Equipment_Recovery & First Aid Equipment_Hard Hat | C4342: N | D4342: Z | E4342: Emergency Equipment | F4342: C | G4342: Recovery & First Aid Equipment | H4342: Q | I4342: Hard Hat | J4342: Azuma
A4343: ZCR | B4343: Emergency Equipment_Recovery & First Aid Equipment_Hi Vis Vests | C4343: N | D4343: Z | E4343: Emergency Equipment | F4343: C | G4343: Recovery & First Aid Equipment | H4343: R | I4343: Hi Vis Vests | J4343: Azuma
A4344: ZCS | B4344: Emergency Equipment_Recovery & First Aid Equipment_Hose (BP) | C4344: N | D4344: Z | E4344: Emergency Equipment | F4344: C | G4344: Recovery & First Aid Equipment | H4344: S | I4344: Hose (BP) | J4344: Azuma
A4345: ZCT | B4345: Emergency Equipment_Recovery & First Aid Equipment_Hose (MRP) | C4345: N | D4345: Z | E4345: Emergency Equipment | F4345: C | G4345: Recovery & First Aid Equipment | H4345: T | I4345: Hose (MRP) | J4345: Azuma
A4346: ZCU | B4346: Emergency Equipment_Recovery & First Aid Equipment_Ladder (Non-Conductive) | C4346: N | D4346: Z | E4346: Emergency Equipment | F4346: C | G4346: Recovery & First Aid Equipment | H4346: U | I4346: Ladder (Non-Conductive) | J4346: Azuma
A4347: ZCV | B4347: Emergency Equipment_Recovery & First Aid Equipment_Laminate Sheets | C4347: N | D4347: Z | E4347: Emergency Equipment | F4347: C | G4347: Recovery & First Aid Equipment | H4347: V | I4347: Laminate Sheets | J4347: Azuma
A4348: ZCW | B4348: Emergency Equipment_Recovery & First Aid Equipment_Light Sticks (Box of 10) | C4348: N | D4348: Z | E4348: Emergency Equipment | F4348: C | G4348: Recovery & First Aid Equipment | H4348: W | I4348: Light Sticks (Box of 10) | J4348: Azuma
A4349: ZCX | B4349: Emergency Equipment_Recovery & First Aid Equipment_Multi-Purpose Saw | C4349: N | D4349: Z | E4349: Emergency Equipment | F4349: C | G4349: Recovery & First Aid Equipment | H4349: X | I4349: Multi-Purpose Saw | J4349: Azuma
A4350: ZCY | B4350: Emergency Equipment_Recovery & First Aid Equipment_Nylon Rope | C4350: N | D4350: Z | E4350: Emergency Equipment | F4350: C | G4350: Recovery & First Aid Equipment | H4350: Y | I4350: Nylon Rope | J4350: Azuma
A4351: ZCZ | B4351: Emergency Equipment_Recovery & First Aid Equipment_Pair of Gloves | C4351: N | D4351: Z | E4351: Emergency Equipment | F4351: C | G4351: Recovery & First Aid Equipment | H4351: Z | I4351: Pair of Gloves | J4351: Azuma
